Workbook

Sheet PARAMS
A1: Paramètre | B1: Valeur | C1: Description
A2: nb_jours_ouvres_an | B2: 264 | C2: Nombre de jours ouvrés par an (conversion annuel -> jour)
A3: heures_par_jour | B3: 8 | C3: Heures de travail par jour
A4: idle_minutes | B4: 0 | C4: Marge d'inactivité (minutes/jour)
A5: productivite_pct | B5: 100 | C5: Productivité (%)
A6: colis_par_sac | B6: 5 | C6: sac = N colis

Sheet INPUT_VOLUMES
A1: sens_code | B1: flux_code | C1: segment_code | D1: volume_annuel | E1: commentaire | F1: key
A2: ARRIVEE | B2: AMANA | C2: GLOBAL | D2: 50000 | E2: Saisie volume annuel | F2: =UPPER(TRIM(SUBSTITUTE(A2," ",""))) & "|" & UPPER(TRIM(SUBSTITUTE(B2," ",""))) & "|" & UPPER(TRIM(SUBSTITUTE(C2," ",""))) -> ARRIVEE|AMANA|GLOBAL
A3: ARRIVEE | B3: AMANA | C3: PARTICULIER | D3: 0 | E3: Saisie volume annuel | F3: =UPPER(TRIM(SUBSTITUTE(A3," ",""))) & "|" & UPPER(TRIM(SUBSTITUTE(B3," ",""))) & "|" & UPPER(TRIM(SUBSTITUTE(C3," ",""))) -> ARRIVEE|AMANA|PARTICULIER
A4: ARRIVEE | B4: AMANA | C4: PRO_B2B | D4: 0 | E4: Saisie volume annuel | F4: =UPPER(TRIM(SUBSTITUTE(A4," ",""))) & "|" & UPPER(TRIM(SUBSTITUTE(B4," ",""))) & "|" & UPPER(TRIM(SUBSTITUTE(C4," ",""))) -> ARRIVEE|AMANA|PRO_B2B
A5: ARRIVEE | B5: AMANA | C5: DISTRIBUTION | D5: 0 | E5: Saisie volume annuel | F5: =UPPER(TRIM(SUBSTITUTE(A5," ",""))) & "|" & UPPER(TRIM(SUBSTITUTE(B5," ",""))) & "|" & UPPER(TRIM(SUBSTITUTE(C5," ",""))) -> ARRIVEE|AMANA|DISTRIBUTION
A6: ARRIVEE | B6: AMANA | C6: AXES | D6: 0 | E6: Saisie volume annuel | F6: =UPPER(TRIM(SUBSTITUTE(A6," ",""))) & "|" & UPPER(TRIM(SUBSTITUTE(B6," ",""))) & "|" & UPPER(TRIM(SUBSTITUTE(C6," ",""))) -> ARRIVEE|AMANA|AXES
A7: ARRIVEE | B7: CO | C7: GLOBAL | D7: 6000 | E7: Saisie volume annuel | F7: =UPPER(TRIM(SUBSTITUTE(A7," ",""))) & "|" & UPPER(TRIM(SUBSTITUTE(B7," ",""))) & "|" & UPPER(TRIM(SUBSTITUTE(C7," ",""))) -> ARRIVEE|CO|GLOBAL
A8: ARRIVEE | B8: CO | C8: PARTICULIER | D8: 0 | E8: Saisie volume annuel | F8: =UPPER(TRIM(SUBSTITUTE(A8," ",""))) & "|" & UPPER(TRIM(SUBSTITUTE(B8," ",""))) & "|" & UPPER(TRIM(SUBSTITUTE(C8," ",""))) -> ARRIVEE|CO|PARTICULIER
A9: ARRIVEE | B9: CO | C9: PRO_B2B | D9: 0 | E9: Saisie volume annuel | F9: =UPPER(TRIM(SUBSTITUTE(A9," ",""))) & "|" & UPPER(TRIM(SUBSTITUTE(B9," ",""))) & "|" & UPPER(TRIM(SUBSTITUTE(C9," ",""))) -> ARRIVEE|CO|PRO_B2B
A10: ARRIVEE | B10: CO | C10: DISTRIBUTION | D10: 0 | E10: Saisie volume annuel | F10: =UPPER(TRIM(SUBSTITUTE(A10," ",""))) & "|" & UPPER(TRIM(SUBSTITUTE(B10," ",""))) & "|" & UPPER(TRIM(SUBSTITUTE(C10," ",""))) -> ARRIVEE|CO|DISTRIBUTION
A11: ARRIVEE | B11: CO | C11: AXES | D11: 0 | E11: Saisie volume annuel | F11: =UPPER(TRIM(SUBSTITUTE(A11," ",""))) & "|" & UPPER(TRIM(SUBSTITUTE(B11," ",""))) & "|" & UPPER(TRIM(SUBSTITUTE(C11," ",""))) -> ARRIVEE|CO|AXES
A12: ARRIVEE | B12: CR | C12: GLOBAL | D12: 0 | E12: Saisie volume annuel | F12: =UPPER(TRIM(SUBSTITUTE(A12," ",""))) & "|" & UPPER(TRIM(SUBSTITUTE(B12," ",""))) & "|" & UPPER(TRIM(SUBSTITUTE(C12," ",""))) -> ARRIVEE|CR|GLOBAL
A13: ARRIVEE | B13: CR | C13: PARTICULIER | D13: 0 | E13: Saisie volume annuel | F13: =UPPER(TRIM(SUBSTITUTE(A13," ",""))) & "|" & UPPER(TRIM(SUBSTITUTE(B13," ",""))) & "|" & UPPER(TRIM(SUBSTITUTE(C13," ",""))) -> ARRIVEE|CR|PARTICULIER
... A34: DEPART | B34: CO | C34: PRO_B2B | D34: 0 | E34: Saisie volume annuel | F34: =UPPER(TRIM(SUBSTITUTE(A34," ",""))) & "|" & UPPER(TRIM(SUBSTITUTE(B34," ",""))) & "|" & UPPER(TRIM(SUBSTITUTE(C34," ",""))) -> DEPART|CO|PRO_B2B
A35: DEPART | B35: CO | C35: DISTRIBUTION | D35: 50000 | E35: Saisie volume annuel | F35: =TRIM(SUBSTITUTE(SUBSTITUTE(A35&"|"&B35&"|"&C35,CHAR(10),""),CHAR(13),"")) -> DEPART|CO|DISTRIBUTION
A36: DEPART | B36: CO | C36: AXES | D36: 0 | E36: Saisie volume annuel | F36: =TRIM(SUBSTITUTE(SUBSTITUTE(A36&"|"&B36&"|"&C36,CHAR(10),""),CHAR(13),"")) -> DEPART|CO|AXES
A37: DEPART | B37: CR | C37: GLOBAL | D37: 0 | E37: Saisie volume annuel | F37: =TRIM(SUBSTITUTE(SUBSTITUTE(A37&"|"&B37&"|"&C37,CHAR(10),""),CHAR(13),"")) -> DEPART|CR|GLOBAL
A38: DEPART | B38: CR | C38: PARTICULIER | D38: 0 | E38: Saisie volume annuel | F38: =TRIM(SUBSTITUTE(SUBSTITUTE(A38&"|"&B38&"|"&C38,CHAR(10),""),CHAR(13),"")) -> DEPART|CR|PARTICULIER
A39: DEPART | B39: CR | C39: PRO_B2B | D39: 0 | E39: Saisie volume annuel | F39: =TRIM(SUBSTITUTE(SUBSTITUTE(A39&"|"&B39&"|"&C39,CHAR(10),""),CHAR(13),"")) -> DEPART|CR|PRO_B2B
A40: DEPART | B40: CR | C40: DISTRIBUTION | D40: 0 | E40: Saisie volume annuel | F40: =TRIM(SUBSTITUTE(SUBSTITUTE(A40&"|"&B40&"|"&C40,CHAR(10),""),CHAR(13),"")) -> DEPART|CR|DISTRIBUTION
A41: DEPART | B41: CR | C41: AXES | D41: 0 | E41: Saisie volume annuel | F41: =TRIM(SUBSTITUTE(SUBSTITUTE(A41&"|"&B41&"|"&C41,CHAR(10),""),CHAR(13),"")) -> DEPART|CR|AXES
A42: DEPART | B42: EB | C42: GLOBAL | D42: 0 | E42: Saisie volume annuel | F42: =TRIM(SUBSTITUTE(SUBSTITUTE(A42&"|"&B42&"|"&C42,CHAR(10),""),CHAR(13),"")) -> DEPART|EB|GLOBAL
A43: DEPART | B43: EB | C43: PARTICULIER | D43: 0 | E43: Saisie volume annuel | F43: =TRIM(SUBSTITUTE(SUBSTITUTE(A43&"|"&B43&"|"&C43,CHAR(10),""),CHAR(13),"")) -> DEPART|EB|PARTICULIER
A44: DEPART | B44: EB | C44: PRO_B2B | D44: 0 | E44: Saisie volume annuel | F44: =TRIM(SUBSTITUTE(SUBSTITUTE(A44&"|"&B44&"|"&C44,CHAR(10),""),CHAR(13),"")) -> DEPART|EB|PRO_B2B
A45: DEPART | B45: EB | C45: DISTRIBUTION | D45: 0 | E45: Saisie volume annuel | F45: =TRIM(SUBSTITUTE(SUBSTITUTE(A45&"|"&B45&"|"&C45,CHAR(10),""),CHAR(13),"")) -> DEPART|EB|DISTRIBUTION
A46: DEPART | B46: EB | C46: AXES | D46: 0 | E46: Saisie volume annuel | F46: =TRIM(SUBSTITUTE(SUBSTITUTE(A46&"|"&B46&"|"&C46,CHAR(10),""),CHAR(13),"")) -> DEPART|EB|AXES
... A53: RECUP | B53: AMANA | C53: PARTICULIER | D53: 0 | E53: Guichet récupération (colis client) | F53: =TRIM(SUBSTITUTE(SUBSTITUTE(A53&"|"&B53&"|"&C53,CHAR(10),""),CHAR(13),"")) -> RECUP|AMANA|PARTICULIER

Sheet Feuil1
A1: centre_poste_id | B1: seq | C1: moyenne_min | D1: nom_tache | E1: flux_id | F1: sens_id | G1: segment_id | H1: id | I1: poste_id | J1: label
A2: 8284 | B2: 12 | C2: 3.625 | D2: Dépôt colis par le client | E2: 1 | F2: 2 | G2: 2 | H2: 8284 | I2: 151 | J2: GUICHETIER
A3: 8284 | B3: 13 | C3: 4.355 | D3: Récupération colis par le client | E3: 1 | F3: 3 | G3: 2 | H3: 8284 | I3: 151 | J3: GUICHETIER
A4: 8284 | B4: 41 | C4: 0.20166667 | D4: Tri par administration | E4: 3 | F4: 1 | G4: 1 | H4: 8284 | I4: 151 | J4: GUICHETIER
A5: 8284 | B5: 42 | C5: 0.64166667 | D5: Envoi Courrier Recommandé | E5: 3 | F5: 4 | G5: 1 | H5: 8284 | I5: 151 | J5: GUICHETIER
A6: 8284 | B6: 43 | C6: 0.58333333 | D6: Récupération CR | E6: 3 | F6: 3 | G6: 2 | H6: 8284 | I6: 151 | J6: GUICHETIER
A7: 8284 | B7: 45 | C7: NULL | D7: Dépôt CO | E7: 2 | F7: 2 | G7: 2 | H7: 8284 | I7: 151 | J7: GUICHETIER
A8: 8284 | B8: 46 | C8: 0.63333333 | D8: Scan DNL et retour info | E8: 2 | F8: 1 | G8: 1 | H8: 8284 | I8: 151 | J8: GUICHETIER
A9: 8284 | B9: 60 | C9: 0.205 | D9: Expédition | E9: 2 | F9: 4 | G9: 2 | H9: 8284 | I9: 151 | J9: GUICHETIER
A10: 8284 | B10: 61 | C10: 0.41166667 | D10: Récupération facture MAG | E10: 2 | F10: 4 | G10: 2 | H10: 8284 | I10: 151 | J10: GUICHETIER
A11: 8284 | B11: 62 | C11: NULL | D11: Passation sur Registre | E11: 2 | F11: 4 | G11: 2 | H11: 8284 | I11: 151 | J11: GUICHETIER
A12: 8284 | B12: 63 | C12: 0.19 | D12: Edition PART | E12: 2 | F12: 4 | G12: 2 | H12: 8284 | I12: 151 | J12: GUICHETIER
A13: 8285 | B13: 5 | C13: 0.18 | D13: Tri & Répartition entre : PP, GP | E13: 1 | F13: 1 | G13: 1 | H13: 8285 | I13: 169 | J13: TRIEUR
A14: 8285 | B14: 37 | C14: NULL | D14: Tri Courrier | E14: 3 | F14: 1 | G14: 1 | H14: 8285 | I14: 169 | J14: TRIEUR
A15: 8286 | B15: 71 | C15: NULL | D15: Etat de la caisse | E15: 5 | F15: 1 | G15: 1 | H15: 8286 | I15: 55 | J15: CHEF DE CENTRE
A16: 8286 | B16: 72 | C16: 5 | D16: BP Intélligente | E16: 5 | F16: 1 | G16: 1 | H16: 8286 | I16: 55 | J16: CHEF DE CENTRE
A17: 8286 | B17: 73 | C17: 5 | D17: Suivi rélaisations commerciales | E17: 5 | F17: 1 | G17: 1 | H17: 8286 | I17: 55 | J17: CHEF DE CENTRE
A18: 8286 | B18: 74 | C18: NULL | D18: Canevas HS | E18: 5 | F18: 1 | G18: 1 | H18: 8286 | I18: 55 | J18: CHEF DE CENTRE
A19: 8286 | B19: 75 | C19: NULL | D19: Pointag intérimaires | E19: 5 | F19: 1 | G19: 1 | H19: 8286 | I19: 55 | J19: CHEF DE CENTRE
A20: 8286 | B20: 76 | C20: NULL | D20: Suivi Gardiennage et femmes de ménage | E20: 5 | F20: 1 | G20: 1 | H20: 8286 | I20: 55 | J20: CHEF DE CENTRE
A21: 8286 | B21: 77 | C21: NULL | D21: Suivi des absences | E21: 5 | F21: 1 | G21: 1 | H21: 8286 | I21: 55 | J21: CHEF DE CENTRE
A22: 8286 | B22: 78 | C22: NULL | D22: Rapport Activité (Echantillonnage pour vérifer statut, poids, contact… | E22: 5 | F22: 1 | G22: 1 | H22: 8286 | I22: 55 | J22: CHEF DE CENTRE
A23: 8288 | B23: 1 | C23: 0.2 | D23: Déchargement VAN Colis | E23: 1 | F23: 1 | G23: 1 | H23: 8288 | I23: 301 | J23: Agent opération
A24: 8288 | B24: 2 | C24: 0.2 | D24: Déchargement VAN Sac | E24: 1 | F24: 1 | G24: 1 | H24: 8288 | I24: 301 | J24: Agent opération
A25: 8288 | B25: 3 | C25: 0.645 | D25: Ouverture sac | E25: 1 | F25: 1 | G25: 1 | H25: 8288 | I25: 301 | J25: Agent opération
A26: 8288 | B26: 4 | C26: 0.02 | D26: vidage sac | E26: 1 | F26: 1 | G26: 1 | H26: 8288 | I26: 301 | J26: Agent opération
A27: 8288 | B27: 6 | C27: 0.033333333 | D27: Scan & Réception SI | E27: 1 | F27: 1 | G27: 1 | H27: 8288 | I27: 301 | J27: Agent opération
A28: 8288 | B28: 7 | C28: 0.033333333 | D28: Enregistrement sur PART 125 | E28: 1 | F28: 1 | G28: 1 | H28: 8288 | I28: 301 | J28: Agent opération
A29: 8288 | B29: 8 | C29: 0.24666667 | D29: Affectation Guichet | E29: 1 | F29: 1 | G29: 1 | H29: 8288 | I29: 301 | J29: Agent opération
A30: 8288 | B30: 9 | C30: 0.02 | D30: Remise avisés au guichet | E30: 1 | F30: 3 | G30: 2 | H30: 8288 | I30: 301 | J30: Agent opération
A31: 8288 | B31: 10 | C31: 0.4 | D31: Préparatin fichier excel | E31: 1 | F31: 4 | G31: 1 | H31: 8288 | I31: 301 | J31: Agent opération
A32: 8288 | B32: 11 | C32: 0.005 | D32: Scan et édition DNL | E32: 1 | F32: 1 | G32: 1 | H32: 8288 | I32: 301 | J32: Agent opération
A33: 8288 | B33: 14 | C33: 0.01 | D33: Etat Levée | E33: 1 | F33: 1 | G33: 1 | H33: 8288 | I33: 301 | J33: Agent opération
A34: 8288 | B34: 15 | C34: 0.35666667 | D34: Récupération Physique colis | E34: 1 | F34: 1 | G34: 1 | H34: 8288 | I34: 301 | J34: Agent opération
A35: 8288 | B35: 16 | C35: NULL | D35: Passation Vs Guichet | E35: 1 | F35: 4 | G35: 1 | H35: 8288 | I35: 301 | J35: Agent opération
A36: 8288 | B36: 17 | C36: 0.16 | D36: Réception | E36: 1 | F36: 1 | G36: 1 | H36: 8288 | I36: 301 | J36: Agent opération
A37: 8288 | B37: 18 | C37: NULL | D37: Numérotage | E37: 1 | F37: 1 | G37: 1 | H37: 8288 | I37: 301 | J37: Agent opération
A38: 8288 | B38: 19 | C38: 0.19833333 | D38: Mise en sac | E38: 1 | F38: 4 | G38: 1 | H38: 8288 | I38: 301 | J38: Agent opération
A39: 8288 | B39: 20 | C39: 0.16666667 | D39: Expédition | E39: 1 | F39: 4 | G39: 1 | H39: 8288 | I39: 301 | J39: Agent opération
A40: 8288 | B40: 21 | C40: 0.21666667 | D40: classement en cabine instance | E40: 1 | F40: 3 | G40: 2 | H40: 8288 | I40: 301 | J40: Agent opération
A41: 8288 | B41: 22 | C41: 0.4 | D41: contrôle physique | E41: 1 | F41: 1 | G41: 1 | H41: 8288 | I41: 301 | J41: Agent opération
A42: 8288 | B42: 23 | C42: 0.17666667 | D42: création dépeche | E42: 1 | F42: 4 | G42: 1 | H42: 8288 | I42: 301 | J42: Agent opération
A43: 8288 | B43: 24 | C43: 0.031666667 | D43: Edition PART | E43: 1 | F43: 4 | G43: 1 | H43: 8288 | I43: 301 | J43: Agent opération
A44: 8288 | B44: 25 | C44: 0.18 | D44: fermeture sac | E44: 1 | F44: 4 | G44: 1 | H44: 8288 | I44: 301 | J44: Agent opération
A45: 8288 | B45: 26 | C45: 0.35833333 | D45: Chargement Camion Colis | E45: 1 | F45: 4 | G45: 1 | H45: 8288 | I45: 301 | J45: Agent opération
A46: 8288 | B46: 27 | C46: 0.22833333 | D46: Chargement Camion Sac | E46: 1 | F46: 4 | G46: 1 | H46: 8288 | I46: 301 | J46: Agent opération
A47: 8288 | B47: 30 | C47: NULL | D47: Réception courrier avisé sur SI COM | E47: 2 | F47: 1 | G47: 2 | H47: 8288 | I47: 301 | J47: Agent opération
A48: 8288 | B48: 31 | C48: 0.43333333 | D48: Affectation : Avisé, Abonné, Vaguemaster … | E48: 3 | F48: 1 | G48: 2 | H48: 8288 | I48: 301 | J48: Agent opération
A49: 8288 | B49: 32 | C49: 0.038333333 | D49: Notification envoi avisé client boite postale | E49: 2 | F49: 1 | G49: 2 | H49: 8288 | I49: 301 | J49: Agent opération
A50: 8288 | B50: 33 | C50: 0.63333333 | D50: Déchargement VAN | E50: 2 | F50: 1 | G50: 1 | H50: 8288 | I50: 301 | J50: Agent opération
A51: 8288 | B51: 34 | C51: NULL | D51: Enregistrement sur PART 125 | E51: 2 | F51: 1 | G51: 1 | H51: 8288 | I51: 301 | J51: Agent opération
A52: 8288 | B52: 35 | C52: 4 | D52: Ouverture sac | E52: 2 | F52: 1 | G52: 1 | H52: 8288 | I52: 301 | J52: Agent opération
A53: 8288 | B53: 36 | C53: 0.58 | D53: Scan & Réception SI | E53: 3 | F53: 1 | G53: 1 | H53: 8288 | I53: 301 | J53: Agent opération
A54: 8288 | B54: 38 | C54: 0.43333333 | D54: Affectation au guichet | E54: 3 | F54: 1 | G54: 2 | H54: 8288 | I54: 301 | J54: Agent opération
A55: 8288 | B55: 39 | C55: 0.6 | D55: Scan et édition DNL | E55: 3 | F55: 1 | G55: 1 | H55: 8288 | I55: 301 | J55: Agent opération
A56: 8288 | B56: 40 | C56: NULL | D56: Remise à l'agent Barid Pro | E56: 3 | F56: 3 | G56: 3 | H56: 8288 | I56: 301 | J56: Agent opération
A57: 8288 | B57: 47 | C57: 0.011666667 | D57: Préparatin fichier excel | E57: 2 | F57: 4 | G57: 1 | H57: 8288 | I57: 301 | J57: Agent opération
A58: 8288 | B58: 48 | C58: 0.4 | D58: Préparation & mise en sac | E58: 2 | F58: 4 | G58: 1 | H58: 8288 | I58: 301 | J58: Agent opération
A59: 8288 | B59: 49 | C59: 0.4 | D59: Remplissage Sac | E59: 2 | F59: 4 | G59: 1 | H59: 8288 | I59: 301 | J59: Agent opération
A60: 8288 | B60: 50 | C60: 0.0066666667 | D60: Edition PART | E60: 2 | F60: 4 | G60: 1 | H60: 8288 | I60: 301 | J60: Agent opération
A61: 8288 | B61: 51 | C61: 0.4 | D61: Chargement VAN | E61: 2 | F61: 4 | G61: 1 | H61: 8288 | I61: 301 | J61: Agent opération
A62: 8288 | B62: 53 | C62: 0.005 | D62: Démarrage Machine | E62: 2 | F62: 4 | G62: 1 | H62: 8288 | I62: 301 | J62: Agent opération
A63: 8288 | B63: 54 | C63: NULL | D63: Mise en service | E63: 2 | F63: 4 | G63: 1 | H63: 8288 | I63: 301 | J63: Agent opération
A64: 8288 | B64: 55 | C64: 0.16666667 | D64: Pesage Courrier | E64: 2 | F64: 1 | G64: 1 | H64: 8288 | I64: 301 | J64: Agent opération
A65: 8288 | B65: 56 | C65: 0.16666667 | D65: Traitement sur la machine MAG (Affranchissement) | E65: 2 | F65: 4 | G65: 1 | H65: 8288 | I65: 301 | J65: Agent opération
A66: 8288 | B66: 57 | C66: 0.21333333 | D66: Réception | E66: 2 | F66: 1 | G66: 1 | H66: 8288 | I66: 301 | J66: Agent opération
A67: 8288 | B67: 58 | C67: 0.38333333 | D67: Renseignement poids en manuel | E67: 2 | F67: 1 | G67: 1 | H67: 8288 | I67: 301 | J67: Agent opération
A68: 8288 | B68: 59 | C68: NULL | D68: Saisie données sur SI COM | E68: 2 | F68: 4 | G68: 1 | H68: 8288 | I68: 301 | J68: Agent opération
A69: 8288 | B69: 69 | C69: NULL | D69: Etat des emballages | E69: 5 | F69: 1 | G69: 1 | H69: 8288 | I69: 301 | J69: Agent opération
A70: 8288 | B70: 70 | C70: NULL | D70: Etat remis aux agents guichet | E70: 5 | F70: 1 | G70: 1 | H70: 8288 | I70: 301 | J70: Agent opération

Sheet CENTRE_TEST
A1: id_tache | B1: seq | C1: POSTE | D1: Centre_poste_id | E1: sens_id | F1: sens_code | G1: unite_mesure(flux_code | H1: flux_id | I1: segment_code | J1: segment_id | K1: nom_tache | L1: moyenne_min
A2: 4966 | B2: 1 | C2: GUICHETIER | D2: 8284 | E2: 1 | F2: =IFERROR(INDEX(code!$B$10:$B$13, MATCH(CENTRE_TEST!$E$2, code!$A$10:$A$13, 0)), "") -> ARRIVEE | G2: Colis | H2: 1 | I2: GLOBAL | J2: 1 | K2: Dépôt colis par le client | L2: 3.625 | M2: =UPPER(TRIM(SUBSTITUTE(SUBSTITUTE(K2,CHAR(10)," "),CHAR(13)," "))) -> DÉPÔT COLIS PAR LE CLIENT
A3: 4967 | B3: 2 | C3: GUICHETIER | D3: 8284 | E3: 1 | F3: =IFERROR(INDEX(code!$B$10:$B$13, MATCH(CENTRE_TEST!$E$3, code!$A$10:$A$13, 0)), "") -> ARRIVEE | G3: Colis | H3: 1 | I3: GLOBAL | J3: 1 | K3: Récupération colis par le client | L3: 4.355 | M3: =TRIM(SUBSTITUTE(SUBSTITUTE(K3,CHAR(10)," "),CHAR(13)," ")) -> Récupération colis par le client
A4: 4968 | B4: 3 | C4: GUICHETIER | D4: 8284 | E4: 1 | F4: =IFERROR(INDEX(code!$B$10:$B$13, MATCH(CENTRE_TEST!$E$4, code!$A$10:$A$13, 0)), "") -> ARRIVEE | G4: Courrier Recommandé | H4: 1 | I4: GLOBAL | J4: 1 | K4: Tri par administration | L4: 0.20166667 | M4: =TRIM(SUBSTITUTE(SUBSTITUTE(K4,CHAR(10)," "),CHAR(13)," ")) -> Tri par administration
A5: 4969 | B5: 4 | C5: GUICHETIER | D5: 8284 | E5: 1 | F5: =IFERROR(INDEX(code!$B$10:$B$13, MATCH(CENTRE_TEST!$E$5, code!$A$10:$A$13, 0)), "") -> ARRIVEE | G5: Courrier Recommandé | H5: 1 | I5: GLOBAL | J5: 1 | K5: Envoi Courrier Recommandé | L5: 0.64166667 | M5: =TRIM(SUBSTITUTE(SUBSTITUTE(K5,CHAR(10)," "),CHAR(13)," ")) -> Envoi Courrier Recommandé
A6: 4970 | B6: 5 | C6: GUICHETIER | D6: 8284 | E6: 1 | F6: =IFERROR(INDEX(code!$B$10:$B$13, MATCH(CENTRE_TEST!$E$6, code!$A$10:$A$13, 0)), "") -> ARRIVEE | G6: Courrier | H6: 1 | I6: GLOBAL | J6: 1 | K6: Récupération CR | L6: 0.58333333 | M6: =TRIM(SUBSTITUTE(SUBSTITUTE(K6,CHAR(10)," "),CHAR(13)," ")) -> Récupération CR
A7: 4971 | B7: 6 | C7: GUICHETIER | D7: 8284 | E7: 1 | F7: =IFERROR(INDEX(code!$B$10:$B$13, MATCH(CENTRE_TEST!$E$7, code!$A$10:$A$13, 0)), "") -> ARRIVEE | G7: Courrier | H7: 1 | I7: GLOBAL | J7: 1 | K7: Dépôt CO | L7: NULL | M7: =TRIM(SUBSTITUTE(SUBSTITUTE(K7,CHAR(10)," "),CHAR(13)," ")) -> Dépôt CO
A8: 4972 | B8: 7 | C8: GUICHETIER | D8: 8284 | E8: 1 | F8: =IFERROR(INDEX(code!$B$10:$B$13, MATCH(CENTRE_TEST!$E$8, code!$A$10:$A$13, 0)), "") -> ARRIVEE | G8: Courrier | H8: 1 | I8: GLOBAL | J8: 1 | K8: Scan DNL et retour info | L8: 0.63333333 | M8: =TRIM(SUBSTITUTE(SUBSTITUTE(K8,CHAR(10)," "),CHAR(13)," ")) -> Scan DNL et retour info
A9: 4973 | B9: 8 | C9: GUICHETIER | D9: 8284 | E9: 1 | F9: =IFERROR(INDEX(code!$B$10:$B$13, MATCH(CENTRE_TEST!$E$9, code!$A$10:$A$13, 0)), "") -> ARRIVEE | G9: Courrier | H9: 1 | I9: GLOBAL | J9: 1 | K9: Expédition | L9: 0.205 | M9: =TRIM(SUBSTITUTE(SUBSTITUTE(K9,CHAR(10)," "),CHAR(13)," ")) -> Expédition
A10: 4974 | B10: 9 | C10: GUICHETIER | D10: 8284 | E10: 1 | F10: =IFERROR(INDEX(code!$B$10:$B$13, MATCH(CENTRE_TEST!$E$10, code!$A$10:$A$13, 0)), "") -> ARRIVEE | G10: Courrier | H10: 1 | I10: GLOBAL | J10: 2 | K10: Récupération facture MAG | L10: 0.41166667 | M10: =TRIM(SUBSTITUTE(SUBSTITUTE(K10,CHAR(10)," "),CHAR(13)," ")) -> Récupération facture MAG
A11: 4975 | B11: 10 | C11: GUICHETIER | D11: 8284 | E11: 1 | F11: =IFERROR(INDEX(code!$B$10:$B$13, MATCH(CENTRE_TEST!$E$11, code!$A$10:$A$13, 0)), "") -> ARRIVEE | G11: Courrier | H11: 1 | I11: GLOBAL | J11: 1 | K11: Passation sur Registre | L11: NULL | M11: =TRIM(SUBSTITUTE(SUBSTITUTE(K11,CHAR(10)," "),CHAR(13)," ")) -> Passation sur Registre
A12: 4976 | B12: 11 | C12: GUICHETIER | D12: 8284 | E12: 1 | F12: =IFERROR(INDEX(code!$B$10:$B$13, MATCH(CENTRE_TEST!$E$12, code!$A$10:$A$13, 0)), "") -> ARRIVEE | G12: Courrier | H12: 1 | I12: GLOBAL | J12: 1 | K12: Edition PART | L12: 0.19 | M12: =TRIM(SUBSTITUTE(SUBSTITUTE(K12,CHAR(10)," "),CHAR(13)," ")) -> Edition PART
A13: 4977 | B13: 12 | C13: TRIEUR | D13: 8285 | E13: 1 | F13: =IFERROR(INDEX(code!$B$10:$B$13, MATCH(CENTRE_TEST!$E$13, code!$A$10:$A$13, 0)), "") -> ARRIVEE | G13: Colis | H13: 1 | I13: GLOBAL | J13: 2 | K13: Tri & Répartition entre : PP, GP | L13: 0.18 | M13: =TRIM(SUBSTITUTE(SUBSTITUTE(K13,CHAR(10)," "),CHAR(13)," ")) -> Tri & Répartition entre : PP, GP
A14: 4978 | B14: 13 | C14: TRIEUR | D14: 8285 | E14: 1 | F14: =IFERROR(INDEX(code!$B$10:$B$13, MATCH(CENTRE_TEST!$E$14, code!$A$10:$A$13, 0)), "") -> ARRIVEE | G14: Courrier Recommandé | H14: 1 | I14: GLOBAL | J14: 2 | K14: Tri Courrier | L14: NULL | M14: =TRIM(SUBSTITUTE(SUBSTITUTE(K14,CHAR(10)," "),CHAR(13)," ")) -> Tri Courrier
A15: 4979 | B15: 14 | C15: CHEF DE CENTRE | D15: 8288 | E15: 1 | F15: =IFERROR(INDEX(code!$B$10:$B$13, MATCH(CENTRE_TEST!$E$15, code!$A$10:$A$13, 0)), "") -> ARRIVEE | G15: 0 | H15: 1 | I15: AXES | J15: 1 | K15: Etat de la caisse | L15: NULL | M15: =TRIM(SUBSTITUTE(SUBSTITUTE(K15,CHAR(10)," "),CHAR(13)," ")) -> Etat de la caisse
A16: 4980 | B16: 15 | C16: CHEF DE CENTRE | D16: 8288 | E16: 1 | F16: =IFERROR(INDEX(code!$B$10:$B$13, MATCH(CENTRE_TEST!$E$16, code!$A$10:$A$13, 0)), "") -> ARRIVEE | G16: 0 | H16: 1 | I16: AXES | J16: 1 | K16: BP Intélligente | L16: 5 | M16: =TRIM(SUBSTITUTE(SUBSTITUTE(K16,CHAR(10)," "),CHAR(13)," ")) -> BP Intélligente
A17: 4981 | B17: 16 | C17: CHEF DE CENTRE | D17: 8288 | E17: 1 | F17: =IFERROR(INDEX(code!$B$10:$B$13, MATCH(CENTRE_TEST!$E$17, code!$A$10:$A$13, 0)), "") -> ARRIVEE | G17: 0 | H17: 1 | I17: AXES | J17: 1 | K17: Suivi rélaisations commerciales | L17: 5 | M17: =TRIM(SUBSTITUTE(SUBSTITUTE(K17,CHAR(10)," "),CHAR(13)," ")) -> Suivi rélaisations commerciales
A18: 4982 | B18: 17 | C18: CHEF DE CENTRE | D18: 8288 | E18: 1 | F18: =IFERROR(INDEX(code!$B$10:$B$13, MATCH(CENTRE_TEST!$E$18, code!$A$10:$A$13, 0)), "") -> ARRIVEE | G18: 0 | H18: 1 | I18: AXES | J18: 1 | K18: Canevas HS | L18: NULL | M18: =TRIM(SUBSTITUTE(SUBSTITUTE(K18,CHAR(10)," "),CHAR(13)," ")) -> Canevas HS
A19: 4983 | B19: 18 | C19: CHEF DE CENTRE | D19: 8288 | E19: 1 | F19: =IFERROR(INDEX(code!$B$10:$B$13, MATCH(CENTRE_TEST!$E$19, code!$A$10:$A$13, 0)), "") -> ARRIVEE | G19: 0 | H19: 1 | I19: AXES | J19: 1 | K19: Pointag intérimaires | L19: NULL | M19: =TRIM(SUBSTITUTE(SUBSTITUTE(K19,CHAR(10)," "),CHAR(13)," ")) -> Pointag intérimaires
A20: 4984 | B20: 19 | C20: CHEF DE CENTRE | D20: 8288 | E20: 1 | F20: =IFERROR(INDEX(code!$B$10:$B$13, MATCH(CENTRE_TEST!$E$20, code!$A$10:$A$13, 0)), "") -> ARRIVEE | G20: 0 | H20: 1 | I20: AXES | J20: 1 | K20: Suivi Gardiennage et femmes de ménage | L20: NULL | M20: =TRIM(SUBSTITUTE(SUBSTITUTE(K20,CHAR(10)," "),CHAR(13)," ")) -> Suivi Gardiennage et femmes de ménage
A21: 4985 | B21: 20 | C21: CHEF DE CENTRE | D21: 8288 | E21: 1 | F21: =IFERROR(INDEX(code!$B$10:$B$13, MATCH(CENTRE_TEST!$E$21, code!$A$10:$A$13, 0)), "") -> ARRIVEE | G21: 0 | H21: 1 | I21: AXES | J21: 1 | K21: Suivi des absences | L21: NULL | M21: =TRIM(SUBSTITUTE(SUBSTITUTE(K21,CHAR(10)," "),CHAR(13)," ")) -> Suivi des absences
A22: 4986 | B22: 21 | C22: CHEF DE CENTRE | D22: 8288 | E22: 1 | F22: =IFERROR(INDEX(code!$B$10:$B$13, MATCH(CENTRE_TEST!$E$22, code!$A$10:$A$13, 0)), "") -> ARRIVEE | G22: 0 | H22: 1 | I22: AXES | J22: 2 | K22: Rapport Activité (Echantillonnage pour vérifer statut, poids, contact… | L22: NULL | M22: =TRIM(SUBSTITUTE(SUBSTITUTE(K22,CHAR(10)," "),CHAR(13)," ")) -> Rapport Activité (Echantillonnage pour vérifer statut, poids, contact…
A23: 4987 | B23: 22 | C23: Agent opération | D23: 8286 | E23: 1 | F23: =IFERROR(INDEX(code!$B$10:$B$13, MATCH(CENTRE_TEST!$E$23, code!$A$10:$A$13, 0)), "") -> ARRIVEE | G23: Colis | H23: 1 | I23: GLOBAL | J23: 1 | K23: Déchargement VAN Colis | L23: 0.2 | M23: =TRIM(SUBSTITUTE(SUBSTITUTE(K23,CHAR(10)," "),CHAR(13)," ")) -> Déchargement VAN Colis
A24: 4988 | B24: 23 | C24: Agent opération | D24: 8286 | E24: 1 | F24: =IFERROR(INDEX(code!$B$10:$B$13, MATCH(CENTRE_TEST!$E$24, code!$A$10:$A$13, 0)), "") -> ARRIVEE | G24: Sac | H24: 1 | I24: GLOBAL | J24: 1 | K24: Déchargement VAN Sac | L24: 0.2 | M24: =TRIM(SUBSTITUTE(SUBSTITUTE(K24,CHAR(10)," "),CHAR(13)," ")) -> Déchargement VAN Sac
A25: 4989 | B25: 24 | C25: Agent opération | D25: 8286 | E25: 1 | F25: =IFERROR(INDEX(code!$B$10:$B$13, MATCH(CENTRE_TEST!$E$25, code!$A$10:$A$13, 0)), "") -> ARRIVEE | G25: Sac | H25: 1 | I25: GLOBAL | J25: 1 | K25: Ouverture sac | L25: 0.645 | M25: =TRIM(SUBSTITUTE(SUBSTITUTE(K25,CHAR(10)," "),CHAR(13)," ")) -> Ouverture sac
A26: 4990 | B26: 25 | C26: Agent opération | D26: 8286 | E26: 1 | F26: =IFERROR(INDEX(code!$B$10:$B$13, MATCH(CENTRE_TEST!$E$26, code!$A$10:$A$13, 0)), "") -> ARRIVEE | G26: Sac | H26: 1 | I26: GLOBAL | J26: 1 | K26: vidage sac | L26: 0.02 | M26: =TRIM(SUBSTITUTE(SUBSTITUTE(K26,CHAR(10)," "),CHAR(13)," ")) -> vidage sac
A27: 4991 | B27: 26 | C27: Agent opération | D27: 8286 | E27: 1 | F27: =IFERROR(INDEX(code!$B$10:$B$13, MATCH(CENTRE_TEST!$E$27, code!$A$10:$A$13, 0)), "") -> ARRIVEE | G27: Colis | H27: 1 | I27: GLOBAL | J27: 1 | K27: Scan & Réception SI | L27: 0.033333333 | M27: =TRIM(SUBSTITUTE(SUBSTITUTE(K27,CHAR(10)," "),CHAR(13)," ")) -> Scan & Réception SI
A28: 4992 | B28: 27 | C28: Agent opération | D28: 8286 | E28: 1 | F28: =IFERROR(INDEX(code!$B$10:$B$13, MATCH(CENTRE_TEST!$E$28, code!$A$10:$A$13, 0)), "") -> ARRIVEE | G28: Colis | H28: 1 | I28: GLOBAL | J28: 1 | K28: Enregistrement sur PART 125 | L28: 0.033333333 | M28: =TRIM(SUBSTITUTE(SUBSTITUTE(K28,CHAR(10)," "),CHAR(13)," ")) -> Enregistrement sur PART 125
A29: 4993 | B29: 30 | C29: Agent opération | D29: 8286 | E29: 1 | F29: =IFERROR(INDEX(code!$B$10:$B$13, MATCH(CENTRE_TEST!$E$29, code!$A$10:$A$13, 0)), "") -> ARRIVEE | G29: Colis | H29: 2 | I29: GLOBAL | J29: 2 | K29: Affectation Guichet | L29: 0.24666667 | M29: =TRIM(SUBSTITUTE(SUBSTITUTE(K29,CHAR(10)," "),CHAR(13)," ")) -> Affectation Guichet
A30: 4994 | B30: 31 | C30: Agent opération | D30: 8286 | E30: 3 | F30: =IFERROR(INDEX(code!$B$10:$B$13, MATCH(CENTRE_TEST!$E$29, code!$A$10:$A$13, 0)), "") -> ARRIVEE | G30: Colis | H30: 3 | I30: GLOBAL | J30: 2 | K30: Remise avisés au guichet | L30: 0.02 | M30: =TRIM(SUBSTITUTE(SUBSTITUTE(K30,CHAR(10)," "),CHAR(13)," ")) -> Remise avisés au guichet
A31: 4995 | B31: 32 | C31: Agent opération | D31: 8286 | E31: 4 | F31: =IFERROR(INDEX(code!$B$10:$B$13, MATCH(CENTRE_TEST!$E$29, code!$A$10:$A$13, 0)), "") -> ARRIVEE | G31: Colis | H31: 2 | I31: GLOBAL | J31: 2 | K31: Préparatin fichier excel | L31: 0.4 | M31: =TRIM(SUBSTITUTE(SUBSTITUTE(K31,CHAR(10)," "),CHAR(13)," ")) -> Préparatin fichier excel
A32: 4996 | B32: 33 | C32: Agent opération | D32: 8286 | E32: 1 | F32: =IFERROR(INDEX(code!$B$10:$B$13, MATCH(CENTRE_TEST!$E$29, code!$A$10:$A$13, 0)), "") -> ARRIVEE | G32: Colis | H32: 2 | I32: GLOBAL | J32: 1 | K32: Scan et édition DNL | L32: 0.005 | M32: =TRIM(SUBSTITUTE(SUBSTITUTE(K32,CHAR(10)," "),CHAR(13)," ")) -> Scan et édition DNL
A33: 4997 | B33: 34 | C33: Agent opération | D33: 8286 | E33: 1 | F33: =IFERROR(INDEX(code!$B$10:$B$13, MATCH(CENTRE_TEST!$E$29, code!$A$10:$A$13, 0)), "") -> ARRIVEE | G33: Colis | H33: 2 | I33: GLOBAL | J33: 1 | K33: Etat Levée | L33: 0.01 | M33: =TRIM(SUBSTITUTE(SUBSTITUTE(K33,CHAR(10)," "),CHAR(13)," ")) -> Etat Levée
A34: 4998 | B34: 35 | C34: Agent opération | D34: 8286 | E34: 1 | F34: =IFERROR(INDEX(code!$B$10:$B$13, MATCH(CENTRE_TEST!$E$29, code!$A$10:$A$13, 0)), "") -> ARRIVEE | G34: Colis | H34: 2 | I34: GLOBAL | J34: 1 | K34: Récupération Physique colis | L34: 0.35666667 | M34: =TRIM(SUBSTITUTE(SUBSTITUTE(K34,CHAR(10)," "),CHAR(13)," ")) -> Récupération Physique colis
A35: 4999 | B35: 36 | C35: Agent opération | D35: 8286 | E35: 4 | F35: =IFERROR(INDEX(code!$B$10:$B$13, MATCH(CENTRE_TEST!$E$29, code!$A$10:$A$13, 0)), "") -> ARRIVEE | G35: Colis | H35: 3 | I35: GLOBAL | J35: 1 | K35: Passation Vs Guichet | L35: NULL | M35: =TRIM(SUBSTITUTE(SUBSTITUTE(K35,CHAR(10)," "),CHAR(13)," ")) -> Passation Vs Guichet
A36: 5000 | B36: 37 | C36: Agent opération | D36: 8286 | E36: 1 | F36: =IFERROR(INDEX(code!$B$10:$B$13, MATCH(CENTRE_TEST!$E$29, code!$A$10:$A$13, 0)), "") -> ARRIVEE | G36: Colis | H36: 3 | I36: GLOBAL | J36: 1 | K36: Réception | L36: 0.16 | M36: =TRIM(SUBSTITUTE(SUBSTITUTE(K36,CHAR(10)," "),CHAR(13)," ")) -> Réception
A37: 5001 | B37: 38 | C37: Agent opération | D37: 8286 | E37: 1 | F37: =IFERROR(INDEX(code!$B$10:$B$13, MATCH(CENTRE_TEST!$E$29, code!$A$10:$A$13, 0)), "") -> ARRIVEE | G37: Colis | H37: 3 | I37: GLOBAL | J37: 2 | K37: Numérotage | L37: NULL | M37: =TRIM(SUBSTITUTE(SUBSTITUTE(K37,CHAR(10)," "),CHAR(13)," ")) -> Numérotage
A38: 5002 | B38: 39 | C38: Agent opération | D38: 8286 | E38: 4 | F38: =IFERROR(INDEX(code!$B$10:$B$13, MATCH(CENTRE_TEST!$E$29, code!$A$10:$A$13, 0)), "") -> ARRIVEE | G38: Colis | H38: 3 | I38: GLOBAL | J38: 1 | K38: Mise en sac | L38: 0.19833333 | M38: =TRIM(SUBSTITUTE(SUBSTITUTE(K38,CHAR(10)," "),CHAR(13)," ")) -> Mise en sac
A39: 5003 | B39: 40 | C39: Agent opération | D39: 8286 | E39: 4 | F39: =IFERROR(INDEX(code!$B$10:$B$13, MATCH(CENTRE_TEST!$E$29, code!$A$10:$A$13, 0)), "") -> ARRIVEE | G39: Colis | H39: 3 | I39: GLOBAL | J39: 3 | K39: Expédition | L39: 0.16666667 | M39: =TRIM(SUBSTITUTE(SUBSTITUTE(K39,CHAR(10)," "),CHAR(13)," ")) -> Expédition
A40: 5004 | B40: 41 | C40: Agent opération | D40: 8286 | E40: 3 | F40: =IFERROR(INDEX(code!$B$10:$B$13, MATCH(CENTRE_TEST!$E$29, code!$A$10:$A$13, 0)), "") -> ARRIVEE | G40: Colis | H40: 3 | I40: GLOBAL | J40: 1 | K40: classement en cabine instance | L40: 0.21666667 | M40: =TRIM(SUBSTITUTE(SUBSTITUTE(K40,CHAR(10)," "),CHAR(13)," ")) -> classement en cabine instance
A41: 5005 | B41: 42 | C41: Agent opération | D41: 8286 | E41: 1 | F41: =IFERROR(INDEX(code!$B$10:$B$13, MATCH(CENTRE_TEST!$E$29, code!$A$10:$A$13, 0)), "") -> ARRIVEE | G41: Colis | H41: 3 | I41: GLOBAL | J41: 1 | K41: contrôle physique | L41: 0.4 | M41: =TRIM(SUBSTITUTE(SUBSTITUTE(K41,CHAR(10)," "),CHAR(13)," ")) -> contrôle physique
A42: 5006 | B42: 43 | C42: Agent opération | D42: 8286 | E42: 1 | F42: =IFERROR(INDEX(code!$B$10:$B$13, MATCH(CENTRE_TEST!$E$29, code!$A$10:$A$13, 0)), "") -> ARRIVEE | G42: Colis | H42: 3 | I42: GLOBAL | J42: 2 | K42: création dépeche | L42: 0.17666667 | M42: =TRIM(SUBSTITUTE(SUBSTITUTE(K42,CHAR(10)," "),CHAR(13)," ")) -> création dépeche
A43: 5007 | B43: 45 | C43: Agent opération | D43: 8286 | E43: 1 | F43: =IFERROR(INDEX(code!$B$10:$B$13, MATCH(CENTRE_TEST!$E$29, code!$A$10:$A$13, 0)), "") -> ARRIVEE | G43: Colis | H43: 2 | I43: GLOBAL | J43: 2 | K43: Edition PART | L43: 0.031666667 | M43: =TRIM(SUBSTITUTE(SUBSTITUTE(K43,CHAR(10)," "),CHAR(13)," ")) -> Edition PART
A44: 5008 | B44: 46 | C44: Agent opération | D44: 8286 | E44: 1 | F44: =IFERROR(INDEX(code!$B$10:$B$13, MATCH(CENTRE_TEST!$E$29, code!$A$10:$A$13, 0)), "") -> ARRIVEE | G44: Sac | H44: 2 | I44: GLOBAL | J44: 1 | K44: fermeture sac | L44: 0.18 | M44: =TRIM(SUBSTITUTE(SUBSTITUTE(K44,CHAR(10)," "),CHAR(13)," ")) -> fermeture sac
A45: 5009 | B45: 47 | C45: Agent opération | D45: 8286 | E45: 1 | F45: =IFERROR(INDEX(code!$B$10:$B$13, MATCH(CENTRE_TEST!$E$45, code!$A$10:$A$13, 0)), "") -> ARRIVEE | G45: Colis | H45: 2 | I45: GLOBAL | J45: 1 | K45: Chargement Camion Colis | L45: 0.35833333 | M45: =TRIM(SUBSTITUTE(SUBSTITUTE(K45,CHAR(10)," "),CHAR(13)," ")) -> Chargement Camion Colis
A46: 5010 | B46: 48 | C46: Agent opération | D46: 8286 | E46: 1 | F46: =IFERROR(INDEX(code!$B$10:$B$13, MATCH(CENTRE_TEST!$E$46, code!$A$10:$A$13, 0)), "") -> ARRIVEE | G46: Sac | H46: 2 | I46: GLOBAL | J46: 1 | K46: Chargement Camion Sac | L46: 0.22833333 | M46: =TRIM(SUBSTITUTE(SUBSTITUTE(K46,CHAR(10)," "),CHAR(13)," ")) -> Chargement Camion Sac
A47: 5011 | B47: 49 | C47: Agent opération | D47: 8286 | E47: 1 | F47: =IFERROR(INDEX(code!$B$10:$B$13, MATCH(CENTRE_TEST!$E$47, code!$A$10:$A$13, 0)), "") -> ARRIVEE | G47: Courrier | H47: 2 | I47: GLOBAL | J47: 1 | K47: Réception courrier avisé sur SI COM | L47: NULL | M47: =TRIM(SUBSTITUTE(SUBSTITUTE(K47,CHAR(10)," "),CHAR(13)," ")) -> Réception courrier avisé sur SI COM
A48: 5012 | B48: 50 | C48: Agent opération | D48: 8286 | E48: 1 | F48: =IFERROR(INDEX(code!$B$10:$B$13, MATCH(CENTRE_TEST!$E$48, code!$A$10:$A$13, 0)), "") -> ARRIVEE | G48: Courrier Recommandé | H48: 2 | I48: GLOBAL | J48: 1 | K48: Affectation : Avisé, Abonné, Vaguemaster … | L48: 0.43333333 | M48: =TRIM(SUBSTITUTE(SUBSTITUTE(K48,CHAR(10)," "),CHAR(13)," ")) -> Affectation : Avisé, Abonné, Vaguemaster …
A49: 5013 | B49: 51 | C49: Agent opération | D49: 8286 | E49: 1 | F49: =IFERROR(INDEX(code!$B$10:$B$13, MATCH(CENTRE_TEST!$E$49, code!$A$10:$A$13, 0)), "") -> ARRIVEE | G49: Courrier | H49: 2 | I49: GLOBAL | J49: 1 | K49: Notification envoi avisé client boite postale | L49: 0.038333333 | M49: =TRIM(SUBSTITUTE(SUBSTITUTE(K49,CHAR(10)," "),CHAR(13)," ")) -> Notification envoi avisé client boite postale
A50: 5014 | B50: 53 | C50: Agent opération | D50: 8286 | E50: 1 | F50: =IFERROR(INDEX(code!$B$10:$B$13, MATCH(CENTRE_TEST!$E$50, code!$A$10:$A$13, 0)), "") -> ARRIVEE | G50: Sac | H50: 2 | I50: GLOBAL | J50: 1 | K50: Déchargement VAN | L50: 0.63333333 | M50: =TRIM(SUBSTITUTE(SUBSTITUTE(K50,CHAR(10)," "),CHAR(13)," ")) -> Déchargement VAN
A51: 5015 | B51: 54 | C51: Agent opération | D51: 8286 | E51: 1 | F51: =IFERROR(INDEX(code!$B$10:$B$13, MATCH(CENTRE_TEST!$E$51, code!$A$10:$A$13, 0)), "") -> ARRIVEE | G51: Sac | H51: 2 | I51: GLOBAL | J51: 1 | K51: Enregistrement sur PART 125 sac | L51: NULL | M51: =TRIM(SUBSTITUTE(SUBSTITUTE(K51,CHAR(10)," "),CHAR(13)," ")) -> Enregistrement sur PART 125 sac
A52: 5016 | B52: 55 | C52: Agent opération | D52: 8286 | E52: 1 | F52: =IFERROR(INDEX(code!$B$10:$B$13, MATCH(CENTRE_TEST!$E$52, code!$A$10:$A$13, 0)), "") -> ARRIVEE | G52: Sac | H52: 2 | I52: GLOBAL | J52: 1 | K52: Ouverture sac | L52: 4 | M52: =TRIM(SUBSTITUTE(SUBSTITUTE(K52,CHAR(10)," "),CHAR(13)," ")) -> Ouverture sac
A53: 5017 | B53: 56 | C53: Agent opération | D53: 8286 | E53: 1 | F53: =IFERROR(INDEX(code!$B$10:$B$13, MATCH(CENTRE_TEST!$E$53, code!$A$10:$A$13, 0)), "") -> ARRIVEE | G53: Courrier Recommandé | H53: 2 | I53: GLOBAL | J53: 1 | K53: Scan & Réception SI courrier | L53: 0.58 | M53: =TRIM(SUBSTITUTE(SUBSTITUTE(K53,CHAR(10)," "),CHAR(13)," ")) -> Scan & Réception SI courrier
A54: 5018 | B54: 57 | C54: Agent opération | D54: 8286 | E54: 1 | F54: =IFERROR(INDEX(code!$B$10:$B$13, MATCH(CENTRE_TEST!$E$54, code!$A$10:$A$13, 0)), "") -> ARRIVEE | G54: Courrier Recommandé | H54: 2 | I54: GLOBAL | J54: 1 | K54: Affectation au guichet | L54: 0.43333333 | M54: =TRIM(SUBSTITUTE(SUBSTITUTE(K54,CHAR(10)," "),CHAR(13)," ")) -> Affectation au guichet
A55: 5019 | B55: 58 | C55: Agent opération | D55: 8286 | E55: 1 | F55: =IFERROR(INDEX(code!$B$10:$B$13, MATCH(CENTRE_TEST!$E$55, code!$A$10:$A$13, 0)), "") -> ARRIVEE | G55: Courrier Recommandé | H55: 2 | I55: GLOBAL | J55: 1 | K55: Scan et édition DNL | L55: 0.6 | M55: =TRIM(SUBSTITUTE(SUBSTITUTE(K55,CHAR(10)," "),CHAR(13)," ")) -> Scan et édition DNL
A56: 5020 | B56: 59 | C56: Agent opération | D56: 8286 | E56: 1 | F56: =IFERROR(INDEX(code!$B$10:$B$13, MATCH(CENTRE_TEST!$E$56, code!$A$10:$A$13, 0)), "") -> ARRIVEE | G56: Courrier Recommandé | H56: 2 | I56: GLOBAL | J56: 1 | K56: Remise à l'agent Barid Pro | L56: NULL | M56: =TRIM(SUBSTITUTE(SUBSTITUTE(K56,CHAR(10)," "),CHAR(13)," ")) -> Remise à l'agent Barid Pro
A57: 5021 | B57: 60 | C57: Agent opération | D57: 8286 | E57: 1 | F57: =IFERROR(INDEX(code!$B$10:$B$13, MATCH(CENTRE_TEST!$E$57, code!$A$10:$A$13, 0)), "") -> ARRIVEE | G57: Courrier | H57: 2 | I57: GLOBAL | J57: 2 | K57: Préparatin fichier excel | L57: 0.011666667 | M57: =TRIM(SUBSTITUTE(SUBSTITUTE(K57,CHAR(10)," "),CHAR(13)," ")) -> Préparatin fichier excel
A58: 5022 | B58: 61 | C58: Agent opération | D58: 8286 | E58: 1 | F58: =IFERROR(INDEX(code!$B$10:$B$13, MATCH(CENTRE_TEST!$E$58, code!$A$10:$A$13, 0)), "") -> ARRIVEE | G58: Courrier | H58: 2 | I58: GLOBAL | J58: 2 | K58: Préparation & mise en sac | L58: 0.4 | M58: =TRIM(SUBSTITUTE(SUBSTITUTE(K58,CHAR(10)," "),CHAR(13)," ")) -> Préparation & mise en sac
A59: 5023 | B59: 62 | C59: Agent opération | D59: 8286 | E59: 1 | F59: =IFERROR(INDEX(code!$B$10:$B$13, MATCH(CENTRE_TEST!$E$59, code!$A$10:$A$13, 0)), "") -> ARRIVEE | G59: Sac | H59: 2 | I59: GLOBAL | J59: 2 | K59: Remplissage Sac | L59: 0.4 | M59: =TRIM(SUBSTITUTE(SUBSTITUTE(K59,CHAR(10)," "),CHAR(13)," ")) -> Remplissage Sac
A60: 5024 | B60: 63 | C60: Agent opération | D60: 8286 | E60: 1 | F60: =IFERROR(INDEX(code!$B$10:$B$13, MATCH(CENTRE_TEST!$E$60, code!$A$10:$A$13, 0)), "") -> ARRIVEE | G60: Sac | H60: 2 | I60: GLOBAL | J60: 2 | K60: Edition PART | L60: 0.0066666667 | M60: =TRIM(SUBSTITUTE(SUBSTITUTE(K60,CHAR(10)," "),CHAR(13)," ")) -> Edition PART
A61: 5025 | B61: 69 | C61: Agent opération | D61: 8286 | E61: 1 | F61: =IFERROR(INDEX(code!$B$10:$B$13, MATCH(CENTRE_TEST!$E$61, code!$A$10:$A$13, 0)), "") -> ARRIVEE | G61: Sac | H61: 5 | I61: GLOBAL | J61: 1 | K61: Chargement VAN | L61: 0.4 | M61: =TRIM(SUBSTITUTE(SUBSTITUTE(K61,CHAR(10)," "),CHAR(13)," ")) -> Chargement VAN
A62: 5026 | B62: 70 | C62: Agent opération | D62: 8286 | E62: 1 | F62: =IFERROR(INDEX(code!$B$10:$B$13, MATCH(CENTRE_TEST!$E$62, code!$A$10:$A$13, 0)), "") -> ARRIVEE | G62: Machine | H62: 5 | I62: GLOBAL | J62: 1 | K62: Démarrage Machine | L62: 0.005 | M62: =TRIM(SUBSTITUTE(SUBSTITUTE(K62,CHAR(10)," "),CHAR(13)," ")) -> Démarrage Machine
A63: 5027 | B63: 71 | C63: Agent opération | D63: 8286 | E63: 1 | F63: =IFERROR(INDEX(code!$B$10:$B$13, MATCH(CENTRE_TEST!$E$63, code!$A$10:$A$13, 0)), "") -> ARRIVEE | G63: Machine | H63: 5 | I63: GLOBAL | J63: 1 | K63: Mise en service | L63: NULL | M63: =TRIM(SUBSTITUTE(SUBSTITUTE(K63,CHAR(10)," "),CHAR(13)," ")) -> Mise en service
A64: 5028 | B64: 72 | C64: Agent opération | D64: 8286 | E64: 1 | F64: =IFERROR(INDEX(code!$B$10:$B$13, MATCH(CENTRE_TEST!$E$64, code!$A$10:$A$13, 0)), "") -> ARRIVEE | G64: Courrier | H64: 5 | I64: GLOBAL | J64: 1 | K64: Pesage Courrier | L64: 0.16666667 | M64: =TRIM(SUBSTITUTE(SUBSTITUTE(K64,CHAR(10)," "),CHAR(13)," ")) -> Pesage Courrier
A65: 5029 | B65: 73 | C65: Agent opération | D65: 8286 | E65: 1 | F65: =IFERROR(INDEX(code!$B$10:$B$13, MATCH(CENTRE_TEST!$E$65, code!$A$10:$A$13, 0)), "") -> ARRIVEE | G65: Courrier | H65: 5 | I65: GLOBAL | J65: 1 | K65: Traitement sur la machine MAG (Affranchissement) | L65: 0.16666667 | M65: =TRIM(SUBSTITUTE(SUBSTITUTE(K65,CHAR(10)," "),CHAR(13)," ")) -> Traitement sur la machine MAG (Affranchissement)
A66: 5030 | B66: 74 | C66: Agent opération | D66: 8286 | E66: 1 | F66: =IFERROR(INDEX(code!$B$10:$B$13, MATCH(CENTRE_TEST!$E$66, code!$A$10:$A$13, 0)), "") -> ARRIVEE | G66: Courrier | H66: 5 | I66: GLOBAL | J66: 1 | K66: Réception | L66: 0.21333333 | M66: =TRIM(SUBSTITUTE(SUBSTITUTE(K66,CHAR(10)," "),CHAR(13)," ")) -> Réception
A67: 5031 | B67: 75 | C67: Agent opération | D67: 8286 | E67: 1 | F67: =IFERROR(INDEX(code!$B$10:$B$13, MATCH(CENTRE_TEST!$E$67, code!$A$10:$A$13, 0)), "") -> ARRIVEE | G67: Courrier | H67: 5 | I67: GLOBAL | J67: 1 | K67: Renseignement poids en manuel | L67: 0.38333333 | M67: =TRIM(SUBSTITUTE(SUBSTITUTE(K67,CHAR(10)," "),CHAR(13)," ")) -> Renseignement poids en manuel
A68: 5032 | B68: 76 | C68: Agent opération | D68: 8286 | E68: 1 | F68: =IFERROR(INDEX(code!$B$10:$B$13, MATCH(CENTRE_TEST!$E$68, code!$A$10:$A$13, 0)), "") -> ARRIVEE | G68: Courrier | H68: 5 | I68: GLOBAL | J68: 1 | K68: Saisie données sur SI COM | L68: NULL | M68: =TRIM(SUBSTITUTE(SUBSTITUTE(K68,CHAR(10)," "),CHAR(13)," ")) -> Saisie données sur SI COM
A69: 5033 | B69: 77 | C69: Agent opération | D69: 8286 | E69: 1 | F69: =IFERROR(INDEX(code!$B$10:$B$13, MATCH(CENTRE_TEST!$E$69, code!$A$10:$A$13, 0)), "") -> ARRIVEE | G69: Courrier | H69: 5 | I69: GLOBAL | J69: 1 | K69: Etat des emballages | L69: NULL | M69: =TRIM(SUBSTITUTE(SUBSTITUTE(K69,CHAR(10)," "),CHAR(13)," ")) -> Etat des emballages
A70: 5034 | B70: 78 | C70: Agent opération | D70: 8286 | E70: 1 | F70: =IFERROR(INDEX(code!$B$10:$B$13, MATCH(CENTRE_TEST!$E$70, code!$A$10:$A$13, 0)), "") -> ARRIVEE | G70: Courrier | H70: 5 | I70: GLOBAL | J70: 1 | K70: Etat remis aux agents guichet | L70: NULL | M70: =TRIM(SUBSTITUTE(SUBSTITUTE(K70,CHAR(10)," "),CHAR(13)," ")) -> Etat remis aux agents guichet

Sheet POSTE_SUMMARY
A1: centre_poste_id | B1: POSTE | C1: total_heures_poste | D1: heures_nettes | E1: ETP_calcule | F1: ETP_arrondi
A2: 8288 | B2: =IFERROR( INDEX(CENTRE_TEST!$C:$C, MATCH($A2, CENTRE_TEST!$D:$D, 0) ), "" ) -> CHEF DE CENTRE | C2: =SUMIFS(SIMULATION_CALC!$O:$O,SIMULATION_CALC!$C:$C,$A2) -> 0 | D2: =PARAMS!$B$3 - (PARAMS!$B$4/60) -> 8 | E2: =IFERROR(C2 / D2, 0) -> 0 | F2: =ROUNDUP(E2,0) -> 0
A3: 8285 | B3: =IFERROR( INDEX(CENTRE_TEST!$C:$C, MATCH($A3, CENTRE_TEST!$D:$D, 0) ), "" ) -> TRIEUR | C3: =SUMIFS(SIMULATION_CALC!$O:$O,SIMULATION_CALC!$C:$C,$A3) -> 0.56818182 | D3: =PARAMS!$B$3 - (PARAMS!$B$4/60) -> 8 | E3: =IFERROR(C3 / D3, 0) -> 0.071022727 | F3: =ROUNDUP(E3,0) -> 1
A4: 8286 | B4: =IFERROR( INDEX(CENTRE_TEST!$C:$C, MATCH($A4, CENTRE_TEST!$D:$D, 0) ), "" ) -> Agent opération | C4: =SUMIFS(SIMULATION_CALC!$O:$O,SIMULATION_CALC!$C:$C,$A4) -> 15.601641 | D4: =PARAMS!$B$3 - (PARAMS!$B$4/60) -> 8 | E4: =IFERROR(C4 / D4, 0) -> 1.9502052 | F4: =ROUNDUP(E4,0) -> 2
A5: 8284 | B5: =IFERROR( INDEX(CENTRE_TEST!$C:$C, MATCH($A5, CENTRE_TEST!$D:$D, 0) ), "" ) -> GUICHETIER | C5: =SUMIFS(SIMULATION_CALC!$O:$O,SIMULATION_CALC!$C:$C,$A5) -> 25.955808 | D5: =PARAMS!$B$3 - (PARAMS!$B$4/60) -> 8 | E5: =IFERROR(C5 / D5, 0) -> 3.244476 | F5: =ROUNDUP(E5,0) -> 4
B6: =IFERROR(RECHERCHEX($A6,[2]REF_POSTE!$A:$A,[2]REF_POSTE!$B:$B),"") | C6: =SUM(C2:C5) -> 42.125631 | E6: =SUM(E2:E5) -> 5.2657039 | F6: =ROUND(E6,0) -> 5

Sheet code
A1: id | B1: code | C1: libelle
A2: 1 | B2: GLOBAL | C2: Global
A3: 2 | B3: PARTICULIER | C3: Particulier
A4: 3 | B4: PRO_B2B | C4: Pro - B2B
A5: 4 | B5: DISTRIBUTION | C5: Distribution
A6: 5 | B6: AXES | C6: Axes
A9: id | B9: code | C9: libelle
A10: 1 | B10: ARRIVEE | C10: Arrivée
A11: 2 | B11: DEPOT | C11: Dépôt
A12: 3 | B12: RECUP | C12: Récupération | D12: GUICHET
A13: 4 | B13: DEPART | C13: Départ

Sheet SIMULATION_CALC
A1: id_tache | B1: seq | C1: centre_poste_id | D1: POSTE | E1: nom_tache | F1: unite_mesure | G1: sens_code | H1: flux_code | I1: segment_code | J1: key | K1: volume_annuel_input | L1: volume_jour | M1: volume_applique | N1: chrono_min | O1: heures
A2: 4966 | B2: 1 | C2: 8284 | D2: GUICHETIER | E2: Dépôt colis par le client | F2: Colis | G2: =IFERROR(INDEX(code!$B$10:$B$13, MATCH(CENTRE_TEST!$E$2, code!$A$10:$A$13, 0)), "") -> ARRIVEE | H2: AMANA | I2: =CENTRE_TEST!$I$2 -> GLOBAL | J2: =UPPER(TRIM(SUBSTITUTE(G2," ",""))) & "|" & UPPER(TRIM(SUBSTITUTE(H2," ",""))) & "|" & UPPER(TRIM(SUBSTITUTE(I2," ",""))) -> ARRIVEE|AMANA|GLOBAL | K2: =IFERROR(SUMIFS(INPUT_VOLUMES!$D:$D,INPUT_VOLUMES!$A:$A,$G2,INPUT_VOLUMES!$B:$B,$H2,INPUT_VOLUMES!$C:$C,$I2),0) -> 50000 | L2: =K2/PARAMS!$B$2 -> 189.39394 | M2: =IF(F2="Sac", L2 / PARAMS!$B$6, L2 ) -> 189.39394 | N2: =IFERROR(INDEX(CENTRE_TEST!$L:$L,MATCH(P2,CENTRE_TEST!$M:$M,0)),0) -> 3.625 | O2: =IFERROR( M2 * (N2/60) * (PARAMS!$B$5 / 100), 0) -> 11.442551 | P2: =UPPER(TRIM(SUBSTITUTE(SUBSTITUTE(E2,CHAR(10)," "),CHAR(13)," "))) -> DÉPÔT COLIS PAR LE CLIENT
A3: 4967 | B3: 2 | C3: 8284 | D3: GUICHETIER | E3: Récupération colis par le client | F3: Colis | G3: =IFERROR(INDEX(code!$B$10:$B$13, MATCH(CENTRE_TEST!$E$3, code!$A$10:$A$13, 0)), "") -> ARRIVEE | H3: AMANA | I3: =CENTRE_TEST!$I$3 -> GLOBAL | J3: =UPPER(TRIM(SUBSTITUTE(G3," ",""))) & "|" & UPPER(TRIM(SUBSTITUTE(H3," ",""))) & "|" & UPPER(TRIM(SUBSTITUTE(I3," ",""))) -> ARRIVEE|AMANA|GLOBAL | K3: =IFERROR(SUMIFS(INPUT_VOLUMES!$D:$D,INPUT_VOLUMES!$A:$A,$G3,INPUT_VOLUMES!$B:$B,$H3,INPUT_VOLUMES!$C:$C,$I3),0) -> 50000 | L3: =K3/PARAMS!$B$2 -> 189.39394 | M3: =IF(F3="Sac", L3 / PARAMS!$B$6, L3 ) -> 189.39394 | N3: =IFERROR(INDEX(CENTRE_TEST!$L:$L,MATCH(P3,CENTRE_TEST!$M:$M,0)),0) -> 4.355 | O3: =IFERROR( M3 * (N3/60) * (PARAMS!$B$5 / 100), 0) -> 13.746843 | P3: =UPPER(TRIM(SUBSTITUTE(SUBSTITUTE(E3,CHAR(10)," "),CHAR(13)," "))) -> RÉCUPÉRATION COLIS PAR LE CLIENT
A4: 4968 | B4: 3 | C4: 8284 | D4: GUICHETIER | E4: Tri par administration | F4: Courrier Recommandé | G4: =IFERROR(INDEX(code!$B$10:$B$13, MATCH(CENTRE_TEST!$E$4, code!$A$10:$A$13, 0)), "") -> ARRIVEE | H4: CR | I4: =CENTRE_TEST!$I$4 -> GLOBAL | J4: =UPPER(TRIM(SUBSTITUTE(G4," ",""))) & "|" & UPPER(TRIM(SUBSTITUTE(H4," ",""))) & "|" & UPPER(TRIM(SUBSTITUTE(I4," ",""))) -> ARRIVEE|CR|GLOBAL | K4: =IFERROR(SUMIFS(INPUT_VOLUMES!$D:$D,INPUT_VOLUMES!$A:$A,$G4,INPUT_VOLUMES!$B:$B,$H4,INPUT_VOLUMES!$C:$C,$I4),0) -> 0 | L4: =K4/PARAMS!$B$2 -> 0 | M4: =IF(F4="Sac", L4 / PARAMS!$B$6, L4 ) -> 0 | N4: =IFERROR(INDEX(CENTRE_TEST!$L:$L,MATCH(P4,CENTRE_TEST!$M:$M,0)),0) -> 0.20166667 | O4: =IFERROR( M4 * (N4/60) * (PARAMS!$B$5 / 100), 0) -> 0 | P4: =UPPER(TRIM(SUBSTITUTE(SUBSTITUTE(E4,CHAR(10)," "),CHAR(13)," "))) -> TRI PAR ADMINISTRATION
A5: 4969 | B5: 4 | C5: 8284 | D5: GUICHETIER | E5: Envoi Courrier Recommandé | F5: Courrier Recommandé | G5: =IFERROR(INDEX(code!$B$10:$B$13, MATCH(CENTRE_TEST!$E$5, code!$A$10:$A$13, 0)), "") -> ARRIVEE | H5: CR | I5: =CENTRE_TEST!$I$5 -> GLOBAL | J5: =UPPER(TRIM(SUBSTITUTE(G5," ",""))) & "|" & UPPER(TRIM(SUBSTITUTE(H5," ",""))) & "|" & UPPER(TRIM(SUBSTITUTE(I5," ",""))) -> ARRIVEE|CR|GLOBAL | K5: =IFERROR(SUMIFS(INPUT_VOLUMES!$D:$D,INPUT_VOLUMES!$A:$A,$G5,INPUT_VOLUMES!$B:$B,$H5,INPUT_VOLUMES!$C:$C,$I5),0) -> 0 | L5: =K5/PARAMS!$B$2 -> 0 | M5: =IF(F5="Sac", L5 / PARAMS!$B$6, L5 ) -> 0 | N5: =IFERROR(INDEX(CENTRE_TEST!$L:$L,MATCH(P5,CENTRE_TEST!$M:$M,0)),0) -> 0.64166667 | O5: =IFERROR( M5 * (N5/60) * (PARAMS!$B$5 / 100), 0) -> 0 | P5: =UPPER(TRIM(SUBSTITUTE(SUBSTITUTE(E5,CHAR(10)," "),CHAR(13)," "))) -> ENVOI COURRIER RECOMMANDÉ
A6: 4970 | B6: 5 | C6: 8284 | D6: GUICHETIER | E6: Récupération CR | F6: Courrier | G6: =IFERROR(INDEX(code!$B$10:$B$13, MATCH(CENTRE_TEST!$E$6, code!$A$10:$A$13, 0)), "") -> ARRIVEE | H6: CO | I6: =CENTRE_TEST!$I$6 -> GLOBAL | J6: =UPPER(TRIM(SUBSTITUTE(G6," ",""))) & "|" & UPPER(TRIM(SUBSTITUTE(H6," ",""))) & "|" & UPPER(TRIM(SUBSTITUTE(I6," ",""))) -> ARRIVEE|CO|GLOBAL | K6: =IFERROR(SUMIFS(INPUT_VOLUMES!$D:$D,INPUT_VOLUMES!$A:$A,$G6,INPUT_VOLUMES!$B:$B,$H6,INPUT_VOLUMES!$C:$C,$I6),0) -> 6000 | L6: =K6/PARAMS!$B$2 -> 22.727273 | M6: =IF(F6="Sac", L6 / PARAMS!$B$6, L6 ) -> 22.727273 | N6: =IFERROR(INDEX(CENTRE_TEST!$L:$L,MATCH(P6,CENTRE_TEST!$M:$M,0)),0) -> 0.58333333 | O6: =IFERROR( M6 * (N6/60) * (PARAMS!$B$5 / 100), 0) -> 0.2209596 | P6: =UPPER(TRIM(SUBSTITUTE(SUBSTITUTE(E6,CHAR(10)," "),CHAR(13)," "))) -> RÉCUPÉRATION CR
A7: 4971 | B7: 6 | C7: 8284 | D7: GUICHETIER | E7: Dépôt CO | F7: Courrier | G7: =IFERROR(INDEX(code!$B$10:$B$13, MATCH(CENTRE_TEST!$E$7, code!$A$10:$A$13, 0)), "") -> ARRIVEE | H7: CO | I7: =CENTRE_TEST!$I$7 -> GLOBAL | J7: =UPPER(TRIM(SUBSTITUTE(G7," ",""))) & "|" & UPPER(TRIM(SUBSTITUTE(H7," ",""))) & "|" & UPPER(TRIM(SUBSTITUTE(I7," ",""))) -> ARRIVEE|CO|GLOBAL | K7: =IFERROR(SUMIFS(INPUT_VOLUMES!$D:$D,INPUT_VOLUMES!$A:$A,$G7,INPUT_VOLUMES!$B:$B,$H7,INPUT_VOLUMES!$C:$C,$I7),0) -> 6000 | L7: =K7/PARAMS!$B$2 -> 22.727273 | M7: =IF(F7="Sac", L7 / PARAMS!$B$6, L7 ) -> 22.727273 | N7: =IFERROR(INDEX(CENTRE_TEST!$L:$L,MATCH(P7,CENTRE_TEST!$M:$M,0)),0) -> NULL | O7: =IFERROR( M7 * (N7/60) * (PARAMS!$B$5 / 100), 0) -> 0 | P7: =UPPER(TRIM(SUBSTITUTE(SUBSTITUTE(E7,CHAR(10)," "),CHAR(13)," "))) -> DÉPÔT CO
A8: 4972 | B8: 7 | C8: 8284 | D8: GUICHETIER | E8: Scan DNL et retour info | F8: Courrier | G8: =IFERROR(INDEX(code!$B$10:$B$13, MATCH(CENTRE_TEST!$E$8, code!$A$10:$A$13, 0)), "") -> ARRIVEE | H8: CO | I8: =CENTRE_TEST!$I$8 -> GLOBAL | J8: =UPPER(TRIM(SUBSTITUTE(G8," ",""))) & "|" & UPPER(TRIM(SUBSTITUTE(H8," ",""))) & "|" & UPPER(TRIM(SUBSTITUTE(I8," ",""))) -> ARRIVEE|CO|GLOBAL | K8: =IFERROR(SUMIFS(INPUT_VOLUMES!$D:$D,INPUT_VOLUMES!$A:$A,$G8,INPUT_VOLUMES!$B:$B,$H8,INPUT_VOLUMES!$C:$C,$I8),0) -> 6000 | L8: =K8/PARAMS!$B$2 -> 22.727273 | M8: =IF(F8="Sac", L8 / PARAMS!$B$6, L8 ) -> 22.727273 | N8: =IFERROR(INDEX(CENTRE_TEST!$L:$L,MATCH(P8,CENTRE_TEST!$M:$M,0)),0) -> 0.63333333 | O8: =IFERROR( M8 * (N8/60) * (PARAMS!$B$5 / 100), 0) -> 0.23989899 | P8: =UPPER(TRIM(SUBSTITUTE(SUBSTITUTE(E8,CHAR(10)," "),CHAR(13)," "))) -> SCAN DNL ET RETOUR INFO
A9: 4973 | B9: 8 | C9: 8284 | D9: GUICHETIER | E9: Expédition | F9: Courrier | G9: =IFERROR(INDEX(code!$B$10:$B$13, MATCH(CENTRE_TEST!$E$9, code!$A$10:$A$13, 0)), "") -> ARRIVEE | H9: CO | I9: =CENTRE_TEST!$I$9 -> GLOBAL | J9: =UPPER(TRIM(SUBSTITUTE(G9," ",""))) & "|" & UPPER(TRIM(SUBSTITUTE(H9," ",""))) & "|" & UPPER(TRIM(SUBSTITUTE(I9," ",""))) -> ARRIVEE|CO|GLOBAL | K9: =IFERROR(SUMIFS(INPUT_VOLUMES!$D:$D,INPUT_VOLUMES!$A:$A,$G9,INPUT_VOLUMES!$B:$B,$H9,INPUT_VOLUMES!$C:$C,$I9),0) -> 6000 | L9: =K9/PARAMS!$B$2 -> 22.727273 | M9: =IF(F9="Sac", L9 / PARAMS!$B$6, L9 ) -> 22.727273 | N9: =IFERROR(INDEX(CENTRE_TEST!$L:$L,MATCH(P9,CENTRE_TEST!$M:$M,0)),0) -> 0.205 | O9: =IFERROR( M9 * (N9/60) * (PARAMS!$B$5 / 100), 0) -> 0.077651515 | P9: =UPPER(TRIM(SUBSTITUTE(SUBSTITUTE(E9,CHAR(10)," "),CHAR(13)," "))) -> EXPÉDITION
A10: 4974 | B10: 9 | C10: 8284 | D10: GUICHETIER | E10: Récupération facture MAG | F10: Courrier | G10: =IFERROR(INDEX(code!$B$10:$B$13, MATCH(CENTRE_TEST!$E$10, code!$A$10:$A$13, 0)), "") -> ARRIVEE | H10: CO | I10: =CENTRE_TEST!$I$10 -> GLOBAL | J10: =UPPER(TRIM(SUBSTITUTE(G10," ",""))) & "|" & UPPER(TRIM(SUBSTITUTE(H10," ",""))) & "|" & UPPER(TRIM(SUBSTITUTE(I10," ",""))) -> ARRIVEE|CO|GLOBAL | K10: =IFERROR(SUMIFS(INPUT_VOLUMES!$D:$D,INPUT_VOLUMES!$A:$A,$G10,INPUT_VOLUMES!$B:$B,$H10,INPUT_VOLUMES!$C:$C,$I10),0) -> 6000 | L10: =K10/PARAMS!$B$2 -> 22.727273 | M10: =IF(F10="Sac", L10 / PARAMS!$B$6, L10 ) -> 22.727273 | N10: =IFERROR(INDEX(CENTRE_TEST!$L:$L,MATCH(P10,CENTRE_TEST!$M:$M,0)),0) -> 0.41166667 | O10: =IFERROR( M10 * (N10/60) * (PARAMS!$B$5 / 100), 0) -> 0.15593434 | P10: =UPPER(TRIM(SUBSTITUTE(SUBSTITUTE(E10,CHAR(10)," "),CHAR(13)," "))) -> RÉCUPÉRATION FACTURE MAG
A11: 4975 | B11: 10 | C11: 8284 | D11: GUICHETIER | E11: Passation sur Registre | F11: Courrier | G11: =IFERROR(INDEX(code!$B$10:$B$13, MATCH(CENTRE_TEST!$E$11, code!$A$10:$A$13, 0)), "") -> ARRIVEE | H11: CO | I11: =CENTRE_TEST!$I$11 -> GLOBAL | J11: =UPPER(TRIM(SUBSTITUTE(G11," ",""))) & "|" & UPPER(TRIM(SUBSTITUTE(H11," ",""))) & "|" & UPPER(TRIM(SUBSTITUTE(I11," ",""))) -> ARRIVEE|CO|GLOBAL | K11: =IFERROR(SUMIFS(INPUT_VOLUMES!$D:$D,INPUT_VOLUMES!$A:$A,$G11,INPUT_VOLUMES!$B:$B,$H11,INPUT_VOLUMES!$C:$C,$I11),0) -> 6000 | L11: =K11/PARAMS!$B$2 -> 22.727273 | M11: =IF(F11="Sac", L11 / PARAMS!$B$6, L11 ) -> 22.727273 | N11: =IFERROR(INDEX(CENTRE_TEST!$L:$L,MATCH(P11,CENTRE_TEST!$M:$M,0)),0) -> NULL | O11: =IFERROR( M11 * (N11/60) * (PARAMS!$B$5 / 100), 0) -> 0 | P11: =UPPER(TRIM(SUBSTITUTE(SUBSTITUTE(E11,CHAR(10)," "),CHAR(13)," "))) -> PASSATION SUR REGISTRE
A12: 4976 | B12: 11 | C12: 8284 | D12: GUICHETIER | E12: Edition PART | F12: Courrier | G12: =IFERROR(INDEX(code!$B$10:$B$13, MATCH(CENTRE_TEST!$E$12, code!$A$10:$A$13, 0)), "") -> ARRIVEE | H12: CO | I12: =CENTRE_TEST!$I$12 -> GLOBAL | J12: =UPPER(TRIM(SUBSTITUTE(G12," ",""))) & "|" & UPPER(TRIM(SUBSTITUTE(H12," ",""))) & "|" & UPPER(TRIM(SUBSTITUTE(I12," ",""))) -> ARRIVEE|CO|GLOBAL | K12: =IFERROR(SUMIFS(INPUT_VOLUMES!$D:$D,INPUT_VOLUMES!$A:$A,$G12,INPUT_VOLUMES!$B:$B,$H12,INPUT_VOLUMES!$C:$C,$I12),0) -> 6000 | L12: =K12/PARAMS!$B$2 -> 22.727273 | M12: =IF(F12="Sac", L12 / PARAMS!$B$6, L12 ) -> 22.727273 | N12: =IFERROR(INDEX(CENTRE_TEST!$L:$L,MATCH(P12,CENTRE_TEST!$M:$M,0)),0) -> 0.19 | O12: =IFERROR( M12 * (N12/60) * (PARAMS!$B$5 / 100), 0) -> 0.071969697 | P12: =UPPER(TRIM(SUBSTITUTE(SUBSTITUTE(E12,CHAR(10)," "),CHAR(13)," "))) -> EDITION PART
A13: 4977 | B13: 12 | C13: 8285 | D13: TRIEUR | E13: Tri & Répartition entre : PP, GP | F13: Colis | G13: =IFERROR(INDEX(code!$B$10:$B$13, MATCH(CENTRE_TEST!$E$13, code!$A$10:$A$13, 0)), "") -> ARRIVEE | H13: AMANA | I13: =CENTRE_TEST!$I$13 -> GLOBAL | J13: =UPPER(TRIM(SUBSTITUTE(G13," ",""))) & "|" & UPPER(TRIM(SUBSTITUTE(H13," ",""))) & "|" & UPPER(TRIM(SUBSTITUTE(I13," ",""))) -> ARRIVEE|AMANA|GLOBAL | K13: =IFERROR(SUMIFS(INPUT_VOLUMES!$D:$D,INPUT_VOLUMES!$A:$A,$G13,INPUT_VOLUMES!$B:$B,$H13,INPUT_VOLUMES!$C:$C,$I13),0) -> 50000 | L13: =K13/PARAMS!$B$2 -> 189.39394 | M13: =IF(F13="Sac", L13 / PARAMS!$B$6, L13 ) -> 189.39394 | N13: =IFERROR(INDEX(CENTRE_TEST!$L:$L,MATCH(P13,CENTRE_TEST!$M:$M,0)),0) -> 0.18 | O13: =IFERROR( M13 * (N13/60) * (PARAMS!$B$5 / 100), 0) -> 0.56818182 | P13: =UPPER(TRIM(SUBSTITUTE(SUBSTITUTE(E13,CHAR(10)," "),CHAR(13)," "))) -> TRI & RÉPARTITION ENTRE : PP, GP
A14: 4978 | B14: 13 | C14: 8285 | D14: TRIEUR | E14: Tri Courrier | F14: Courrier Recommandé | G14: =IFERROR(INDEX(code!$B$10:$B$13, MATCH(CENTRE_TEST!$E$14, code!$A$10:$A$13, 0)), "") -> ARRIVEE | H14: AMANA | I14: =CENTRE_TEST!$I$14 -> GLOBAL | J14: =UPPER(TRIM(SUBSTITUTE(G14," ",""))) & "|" & UPPER(TRIM(SUBSTITUTE(H14," ",""))) & "|" & UPPER(TRIM(SUBSTITUTE(I14," ",""))) -> ARRIVEE|AMANA|GLOBAL | K14: =IFERROR(SUMIFS(INPUT_VOLUMES!$D:$D,INPUT_VOLUMES!$A:$A,$G14,INPUT_VOLUMES!$B:$B,$H14,INPUT_VOLUMES!$C:$C,$I14),0) -> 50000 | L14: =K14/PARAMS!$B$2 -> 189.39394 | M14: =IF(F14="Sac", L14 / PARAMS!$B$6, L14 ) -> 189.39394 | N14: =IFERROR(INDEX(CENTRE_TEST!$L:$L,MATCH(P14,CENTRE_TEST!$M:$M,0)),0) -> NULL | O14: =IFERROR( M14 * (N14/60) * (PARAMS!$B$5 / 100), 0) -> 0 | P14: =UPPER(TRIM(SUBSTITUTE(SUBSTITUTE(E14,CHAR(10)," "),CHAR(13)," "))) -> TRI COURRIER
A15: 4979 | B15: 14 | C15: 8288 | D15: CHEF DE CENTRE | E15: Etat de la caisse | F15: NULL | G15: =IFERROR(INDEX(code!$B$10:$B$13, MATCH(CENTRE_TEST!$E$15, code!$A$10:$A$13, 0)), "") -> ARRIVEE | H15: AMANA | I15: =CENTRE_TEST!$I$15 -> AXES | J15: =UPPER(TRIM(SUBSTITUTE(G15," ",""))) & "|" & UPPER(TRIM(SUBSTITUTE(H15," ",""))) & "|" & UPPER(TRIM(SUBSTITUTE(I15," ",""))) -> ARRIVEE|AMANA|AXES | K15: =IFERROR(SUMIFS(INPUT_VOLUMES!$D:$D,INPUT_VOLUMES!$A:$A,$G15,INPUT_VOLUMES!$B:$B,$H15,INPUT_VOLUMES!$C:$C,$I15),0) -> 0 | L15: =K15/PARAMS!$B$2 -> 0 | M15: =IF(F15="Sac", L15 / PARAMS!$B$6, L15 ) -> 0 | N15: =IFERROR(INDEX(CENTRE_TEST!$L:$L,MATCH(P15,CENTRE_TEST!$M:$M,0)),0) -> NULL | O15: =IFERROR( M15 * (N15/60) * (PARAMS!$B$5 / 100), 0) -> 0 | P15: =UPPER(TRIM(SUBSTITUTE(SUBSTITUTE(E15,CHAR(10)," "),CHAR(13)," "))) -> ETAT DE LA CAISSE
A16: 4980 | B16: 15 | C16: 8288 | D16: CHEF DE CENTRE | E16: BP Intélligente | F16: NULL | G16: =IFERROR(INDEX(code!$B$10:$B$13, MATCH(CENTRE_TEST!$E$16, code!$A$10:$A$13, 0)), "") -> ARRIVEE | H16: AMANA | I16: =CENTRE_TEST!$I$16 -> AXES | J16: =UPPER(TRIM(SUBSTITUTE(G16," ",""))) & "|" & UPPER(TRIM(SUBSTITUTE(H16," ",""))) & "|" & UPPER(TRIM(SUBSTITUTE(I16," ",""))) -> ARRIVEE|AMANA|AXES | K16: =IFERROR(SUMIFS(INPUT_VOLUMES!$D:$D,INPUT_VOLUMES!$A:$A,$G16,INPUT_VOLUMES!$B:$B,$H16,INPUT_VOLUMES!$C:$C,$I16),0) -> 0 | L16: =K16/PARAMS!$B$2 -> 0 | M16: =IF(F16="Sac", L16 / PARAMS!$B$6, L16 ) -> 0 | N16: =IFERROR(INDEX(CENTRE_TEST!$L:$L,MATCH(P16,CENTRE_TEST!$M:$M,0)),0) -> 5 | O16: =IFERROR( M16 * (N16/60) * (PARAMS!$B$5 / 100), 0) -> 0 | P16: =UPPER(TRIM(SUBSTITUTE(SUBSTITUTE(E16,CHAR(10)," "),CHAR(13)," "))) -> BP INTÉLLIGENTE
A17: 4981 | B17: 16 | C17: 8288 | D17: CHEF DE CENTRE | E17: Suivi rélaisations commerciales | F17: NULL | G17: =IFERROR(INDEX(code!$B$10:$B$13, MATCH(CENTRE_TEST!$E$17, code!$A$10:$A$13, 0)), "") -> ARRIVEE | H17: AMANA | I17: =CENTRE_TEST!$I$17 -> AXES | J17: =UPPER(TRIM(SUBSTITUTE(G17," ",""))) & "|" & UPPER(TRIM(SUBSTITUTE(H17," ",""))) & "|" & UPPER(TRIM(SUBSTITUTE(I17," ",""))) -> ARRIVEE|AMANA|AXES | K17: =IFERROR(SUMIFS(INPUT_VOLUMES!$D:$D,INPUT_VOLUMES!$A:$A,$G17,INPUT_VOLUMES!$B:$B,$H17,INPUT_VOLUMES!$C:$C,$I17),0) -> 0 | L17: =K17/PARAMS!$B$2 -> 0 | M17: =IF(F17="Sac", L17 / PARAMS!$B$6, L17 ) -> 0 | N17: =IFERROR(INDEX(CENTRE_TEST!$L:$L,MATCH(P17,CENTRE_TEST!$M:$M,0)),0) -> 5 | O17: =IFERROR( M17 * (N17/60) * (PARAMS!$B$5 / 100), 0) -> 0 | P17: =UPPER(TRIM(SUBSTITUTE(SUBSTITUTE(E17,CHAR(10)," "),CHAR(13)," "))) -> SUIVI RÉLAISATIONS COMMERCIALES
A18: 4982 | B18: 17 | C18: 8288 | D18: CHEF DE CENTRE | E18: Canevas HS | F18: NULL | G18: =IFERROR(INDEX(code!$B$10:$B$13, MATCH(CENTRE_TEST!$E$18, code!$A$10:$A$13, 0)), "") -> ARRIVEE | H18: AMANA | I18: =CENTRE_TEST!$I$18 -> AXES | J18: =UPPER(TRIM(SUBSTITUTE(G18," ",""))) & "|" & UPPER(TRIM(SUBSTITUTE(H18," ",""))) & "|" & UPPER(TRIM(SUBSTITUTE(I18," ",""))) -> ARRIVEE|AMANA|AXES | K18: =IFERROR(SUMIFS(INPUT_VOLUMES!$D:$D,INPUT_VOLUMES!$A:$A,$G18,INPUT_VOLUMES!$B:$B,$H18,INPUT_VOLUMES!$C:$C,$I18),0) -> 0 | L18: =K18/PARAMS!$B$2 -> 0 | M18: =IF(F18="Sac", L18 / PARAMS!$B$6, L18 ) -> 0 | N18: =IFERROR(INDEX(CENTRE_TEST!$L:$L,MATCH(P18,CENTRE_TEST!$M:$M,0)),0) -> NULL | O18: =IFERROR( M18 * (N18/60) * (PARAMS!$B$5 / 100), 0) -> 0 | P18: =UPPER(TRIM(SUBSTITUTE(SUBSTITUTE(E18,CHAR(10)," "),CHAR(13)," "))) -> CANEVAS HS
A19: 4983 | B19: 18 | C19: 8288 | D19: CHEF DE CENTRE | E19: Pointag intérimaires | F19: NULL | G19: =IFERROR(INDEX(code!$B$10:$B$13, MATCH(CENTRE_TEST!$E$19, code!$A$10:$A$13, 0)), "") -> ARRIVEE | H19: AMANA | I19: =CENTRE_TEST!$I$19 -> AXES | J19: =UPPER(TRIM(SUBSTITUTE(G19," ",""))) & "|" & UPPER(TRIM(SUBSTITUTE(H19," ",""))) & "|" & UPPER(TRIM(SUBSTITUTE(I19," ",""))) -> ARRIVEE|AMANA|AXES | K19: =IFERROR(SUMIFS(INPUT_VOLUMES!$D:$D,INPUT_VOLUMES!$A:$A,$G19,INPUT_VOLUMES!$B:$B,$H19,INPUT_VOLUMES!$C:$C,$I19),0) -> 0 | L19: =K19/PARAMS!$B$2 -> 0 | M19: =IF(F19="Sac", L19 / PARAMS!$B$6, L19 ) -> 0 | N19: =IFERROR(INDEX(CENTRE_TEST!$L:$L,MATCH(P19,CENTRE_TEST!$M:$M,0)),0) -> NULL | O19: =IFERROR( M19 * (N19/60) * (PARAMS!$B$5 / 100), 0) -> 0 | P19: =UPPER(TRIM(SUBSTITUTE(SUBSTITUTE(E19,CHAR(10)," "),CHAR(13)," "))) -> POINTAG INTÉRIMAIRES
A20: 4984 | B20: 19 | C20: 8288 | D20: CHEF DE CENTRE | E20: Suivi Gardiennage et femmes de ménage | F20: NULL | G20: =IFERROR(INDEX(code!$B$10:$B$13, MATCH(CENTRE_TEST!$E$20, code!$A$10:$A$13, 0)), "") -> ARRIVEE | H20: AMANA | I20: =CENTRE_TEST!$I$20 -> AXES | J20: =UPPER(TRIM(SUBSTITUTE(G20," ",""))) & "|" & UPPER(TRIM(SUBSTITUTE(H20," ",""))) & "|" & UPPER(TRIM(SUBSTITUTE(I20," ",""))) -> ARRIVEE|AMANA|AXES | K20: =IFERROR(SUMIFS(INPUT_VOLUMES!$D:$D,INPUT_VOLUMES!$A:$A,$G20,INPUT_VOLUMES!$B:$B,$H20,INPUT_VOLUMES!$C:$C,$I20),0) -> 0 | L20: =K20/PARAMS!$B$2 -> 0 | M20: =IF(F20="Sac", L20 / PARAMS!$B$6, L20 ) -> 0 | N20: =IFERROR(INDEX(CENTRE_TEST!$L:$L,MATCH(P20,CENTRE_TEST!$M:$M,0)),0) -> NULL | O20: =IFERROR( M20 * (N20/60) * (PARAMS!$B$5 / 100), 0) -> 0 | P20: =UPPER(TRIM(SUBSTITUTE(SUBSTITUTE(E20,CHAR(10)," "),CHAR(13)," "))) -> SUIVI GARDIENNAGE ET FEMMES DE MÉNAGE
A21: 4985 | B21: 20 | C21: 8288 | D21: CHEF DE CENTRE | E21: Suivi des absences | F21: NULL | G21: =IFERROR(INDEX(code!$B$10:$B$13, MATCH(CENTRE_TEST!$E$21, code!$A$10:$A$13, 0)), "") -> ARRIVEE | H21: AMANA | I21: =CENTRE_TEST!$I$21 -> AXES | J21: =UPPER(TRIM(SUBSTITUTE(G21," ",""))) & "|" & UPPER(TRIM(SUBSTITUTE(H21," ",""))) & "|" & UPPER(TRIM(SUBSTITUTE(I21," ",""))) -> ARRIVEE|AMANA|AXES | K21: =IFERROR(SUMIFS(INPUT_VOLUMES!$D:$D,INPUT_VOLUMES!$A:$A,$G21,INPUT_VOLUMES!$B:$B,$H21,INPUT_VOLUMES!$C:$C,$I21),0) -> 0 | L21: =K21/PARAMS!$B$2 -> 0 | M21: =IF(F21="Sac", L21 / PARAMS!$B$6, L21 ) -> 0 | N21: =IFERROR(INDEX(CENTRE_TEST!$L:$L,MATCH(P21,CENTRE_TEST!$M:$M,0)),0) -> NULL | O21: =IFERROR( M21 * (N21/60) * (PARAMS!$B$5 / 100), 0) -> 0 | P21: =UPPER(TRIM(SUBSTITUTE(SUBSTITUTE(E21,CHAR(10)," "),CHAR(13)," "))) -> SUIVI DES ABSENCES
A22: 4986 | B22: 21 | C22: 8288 | D22: CHEF DE CENTRE | E22: Rapport Activité (Echantillonnage pour vérifer statut, poids, contact… | F22: NULL | G22: =IFERROR(INDEX(code!$B$10:$B$13, MATCH(CENTRE_TEST!$E$22, code!$A$10:$A$13, 0)), "") -> ARRIVEE | H22: AMANA | I22: =CENTRE_TEST!$I$22 -> AXES | J22: =UPPER(TRIM(SUBSTITUTE(G22," ",""))) & "|" & UPPER(TRIM(SUBSTITUTE(H22," ",""))) & "|" & UPPER(TRIM(SUBSTITUTE(I22," ",""))) -> ARRIVEE|AMANA|AXES | K22: =IFERROR(SUMIFS(INPUT_VOLUMES!$D:$D,INPUT_VOLUMES!$A:$A,$G22,INPUT_VOLUMES!$B:$B,$H22,INPUT_VOLUMES!$C:$C,$I22),0) -> 0 | L22: =K22/PARAMS!$B$2 -> 0 | M22: =IF(F22="Sac", L22 / PARAMS!$B$6, L22 ) -> 0 | N22: =IFERROR(INDEX(CENTRE_TEST!$L:$L,MATCH(P22,CENTRE_TEST!$M:$M,0)),0) -> NULL | O22: =IFERROR( M22 * (N22/60) * (PARAMS!$B$5 / 100), 0) -> 0 | P22: =UPPER(TRIM(SUBSTITUTE(SUBSTITUTE(E22,CHAR(10)," "),CHAR(13)," "))) -> RAPPORT ACTIVITÉ (ECHANTILLONNAGE POUR VÉRIFER STATUT, POIDS, CONTACT…
A23: 4987 | B23: 22 | C23: 8286 | D23: Agent opération | E23: Déchargement VAN Colis | F23: Colis | G23: =IFERROR(INDEX(code!$B$10:$B$13, MATCH(CENTRE_TEST!$E$23, code!$A$10:$A$13, 0)), "") -> ARRIVEE | H23: AMANA | I23: =CENTRE_TEST!$I$23 -> GLOBAL | J23: =UPPER(TRIM(SUBSTITUTE(G23," ",""))) & "|" & UPPER(TRIM(SUBSTITUTE(H23," ",""))) & "|" & UPPER(TRIM(SUBSTITUTE(I23," ",""))) -> ARRIVEE|AMANA|GLOBAL | K23: =IFERROR(SUMIFS(INPUT_VOLUMES!$D:$D,INPUT_VOLUMES!$A:$A,$G23,INPUT_VOLUMES!$B:$B,$H23,INPUT_VOLUMES!$C:$C,$I23),0) -> 50000 | L23: =K23/PARAMS!$B$2 -> 189.39394 | M23: =IF(F23="Sac", L23 / PARAMS!$B$6, L23 ) -> 189.39394 | N23: =IFERROR(INDEX(CENTRE_TEST!$L:$L,MATCH(P23,CENTRE_TEST!$M:$M,0)),0) -> 0.2 | O23: =IFERROR( M23 * (N23/60) * (PARAMS!$B$5 / 100), 0) -> 0.63131313 | P23: =UPPER(TRIM(SUBSTITUTE(SUBSTITUTE(E23,CHAR(10)," "),CHAR(13)," "))) -> DÉCHARGEMENT VAN COLIS
A24: 4988 | B24: 23 | C24: 8286 | D24: Agent opération | E24: Déchargement VAN Sac | F24: Sac | G24: =IFERROR(INDEX(code!$B$10:$B$13, MATCH(CENTRE_TEST!$E$24, code!$A$10:$A$13, 0)), "") -> ARRIVEE | H24: AMANA | I24: =CENTRE_TEST!$I$24 -> GLOBAL | J24: =UPPER(TRIM(SUBSTITUTE(G24," ",""))) & "|" & UPPER(TRIM(SUBSTITUTE(H24," ",""))) & "|" & UPPER(TRIM(SUBSTITUTE(I24," ",""))) -> ARRIVEE|AMANA|GLOBAL | K24: =IFERROR(SUMIFS(INPUT_VOLUMES!$D:$D,INPUT_VOLUMES!$A:$A,$G24,INPUT_VOLUMES!$B:$B,$H24,INPUT_VOLUMES!$C:$C,$I24),0) -> 50000 | L24: =K24/PARAMS!$B$2 -> 189.39394 | M24: =IF(F24="Sac", L24 / PARAMS!$B$6, L24 ) -> 37.878788 | N24: =IFERROR(INDEX(CENTRE_TEST!$L:$L,MATCH(P24,CENTRE_TEST!$M:$M,0)),0) -> 0.2 | O24: =IFERROR( M24 * (N24/60) * (PARAMS!$B$5 / 100), 0) -> 0.12626263 | P24: =UPPER(TRIM(SUBSTITUTE(SUBSTITUTE(E24,CHAR(10)," "),CHAR(13)," "))) -> DÉCHARGEMENT VAN SAC
A25: 4989 | B25: 24 | C25: 8286 | D25: Agent opération | E25: Ouverture sac | F25: Sac | G25: =IFERROR(INDEX(code!$B$10:$B$13, MATCH(CENTRE_TEST!$E$25, code!$A$10:$A$13, 0)), "") -> ARRIVEE | H25: AMANA | I25: =CENTRE_TEST!$I$25 -> GLOBAL | J25: =UPPER(TRIM(SUBSTITUTE(G25," ",""))) & "|" & UPPER(TRIM(SUBSTITUTE(H25," ",""))) & "|" & UPPER(TRIM(SUBSTITUTE(I25," ",""))) -> ARRIVEE|AMANA|GLOBAL | K25: =IFERROR(SUMIFS(INPUT_VOLUMES!$D:$D,INPUT_VOLUMES!$A:$A,$G25,INPUT_VOLUMES!$B:$B,$H25,INPUT_VOLUMES!$C:$C,$I25),0) -> 50000 | L25: =K25/PARAMS!$B$2 -> 189.39394 | M25: =IF(F25="Sac", L25 / PARAMS!$B$6, L25 ) -> 37.878788 | N25: =IFERROR(INDEX(CENTRE_TEST!$L:$L,MATCH(P25,CENTRE_TEST!$M:$M,0)),0) -> 0.645 | O25: =IFERROR( M25 * (N25/60) * (PARAMS!$B$5 / 100), 0) -> 0.40719697 | P25: =UPPER(TRIM(SUBSTITUTE(SUBSTITUTE(E25,CHAR(10)," "),CHAR(13)," "))) -> OUVERTURE SAC
A26: 4990 | B26: 25 | C26: 8286 | D26: Agent opération | E26: vidage sac | F26: Sac | G26: =IFERROR(INDEX(code!$B$10:$B$13, MATCH(CENTRE_TEST!$E$26, code!$A$10:$A$13, 0)), "") -> ARRIVEE | H26: AMANA | I26: =CENTRE_TEST!$I$26 -> GLOBAL | J26: =UPPER(TRIM(SUBSTITUTE(G26," ",""))) & "|" & UPPER(TRIM(SUBSTITUTE(H26," ",""))) & "|" & UPPER(TRIM(SUBSTITUTE(I26," ",""))) -> ARRIVEE|AMANA|GLOBAL | K26: =IFERROR(SUMIFS(INPUT_VOLUMES!$D:$D,INPUT_VOLUMES!$A:$A,$G26,INPUT_VOLUMES!$B:$B,$H26,INPUT_VOLUMES!$C:$C,$I26),0) -> 50000 | L26: =K26/PARAMS!$B$2 -> 189.39394 | M26: =IF(F26="Sac", L26 / PARAMS!$B$6, L26 ) -> 37.878788 | N26: =IFERROR(INDEX(CENTRE_TEST!$L:$L,MATCH(P26,CENTRE_TEST!$M:$M,0)),0) -> 0.02 | O26: =IFERROR( M26 * (N26/60) * (PARAMS!$B$5 / 100), 0) -> 0.012626263 | P26: =UPPER(TRIM(SUBSTITUTE(SUBSTITUTE(E26,CHAR(10)," "),CHAR(13)," "))) -> VIDAGE SAC
A27: 4991 | B27: 26 | C27: 8286 | D27: Agent opération | E27: Scan & Réception SI | F27: Colis | G27: =IFERROR(INDEX(code!$B$10:$B$13, MATCH(CENTRE_TEST!$E$27, code!$A$10:$A$13, 0)), "") -> ARRIVEE | H27: AMANA | I27: =CENTRE_TEST!$I$27 -> GLOBAL | J27: =UPPER(TRIM(SUBSTITUTE(G27," ",""))) & "|" & UPPER(TRIM(SUBSTITUTE(H27," ",""))) & "|" & UPPER(TRIM(SUBSTITUTE(I27," ",""))) -> ARRIVEE|AMANA|GLOBAL | K27: =IFERROR(SUMIFS(INPUT_VOLUMES!$D:$D,INPUT_VOLUMES!$A:$A,$G27,INPUT_VOLUMES!$B:$B,$H27,INPUT_VOLUMES!$C:$C,$I27),0) -> 50000 | L27: =K27/PARAMS!$B$2 -> 189.39394 | M27: =IF(F27="Sac", L27 / PARAMS!$B$6, L27 ) -> 189.39394 | N27: =IFERROR(INDEX(CENTRE_TEST!$L:$L,MATCH(P27,CENTRE_TEST!$M:$M,0)),0) -> 0.033333333 | O27: =IFERROR( M27 * (N27/60) * (PARAMS!$B$5 / 100), 0) -> 0.10521886 | P27: =UPPER(TRIM(SUBSTITUTE(SUBSTITUTE(E27,CHAR(10)," "),CHAR(13)," "))) -> SCAN & RÉCEPTION SI
A28: 4992 | B28: 27 | C28: 8286 | D28: Agent opération | E28: Enregistrement sur PART 125 | F28: Colis | G28: =IFERROR(INDEX(code!$B$10:$B$13, MATCH(CENTRE_TEST!$E$28, code!$A$10:$A$13, 0)), "") -> ARRIVEE | H28: AMANA | I28: =CENTRE_TEST!$I$28 -> GLOBAL | J28: =UPPER(TRIM(SUBSTITUTE(G28," ",""))) & "|" & UPPER(TRIM(SUBSTITUTE(H28," ",""))) & "|" & UPPER(TRIM(SUBSTITUTE(I28," ",""))) -> ARRIVEE|AMANA|GLOBAL | K28: =IFERROR(SUMIFS(INPUT_VOLUMES!$D:$D,INPUT_VOLUMES!$A:$A,$G28,INPUT_VOLUMES!$B:$B,$H28,INPUT_VOLUMES!$C:$C,$I28),0) -> 50000 | L28: =K28/PARAMS!$B$2 -> 189.39394 | M28: =IF(F28="Sac", L28 / PARAMS!$B$6, L28 ) -> 189.39394 | N28: =IFERROR(INDEX(CENTRE_TEST!$L:$L,MATCH(P28,CENTRE_TEST!$M:$M,0)),0) -> 0.033333333 | O28: =IFERROR( M28 * (N28/60) * (PARAMS!$B$5 / 100), 0) -> 0.10521886 | P28: =UPPER(TRIM(SUBSTITUTE(SUBSTITUTE(E28,CHAR(10)," "),CHAR(13)," "))) -> ENREGISTREMENT SUR PART 125
A29: 4993 | B29: 30 | C29: 8286 | D29: Agent opération | E29: Affectation Guichet | F29: Colis | G29: =IFERROR(INDEX(code!$B$10:$B$13, MATCH(CENTRE_TEST!$E$28, code!$A$10:$A$13, 0)), "") -> ARRIVEE | H29: AMANA | I29: =CENTRE_TEST!$I$29 -> GLOBAL | J29: =UPPER(TRIM(SUBSTITUTE(G29," ",""))) & "|" & UPPER(TRIM(SUBSTITUTE(H29," ",""))) & "|" & UPPER(TRIM(SUBSTITUTE(I29," ",""))) -> ARRIVEE|AMANA|GLOBAL | K29: =IFERROR(SUMIFS(INPUT_VOLUMES!$D:$D,INPUT_VOLUMES!$A:$A,$G29,INPUT_VOLUMES!$B:$B,$H29,INPUT_VOLUMES!$C:$C,$I29),0) -> 50000 | L29: =K29/PARAMS!$B$2 -> 189.39394 | M29: =IF(F29="Sac", L29 / PARAMS!$B$6, L29 ) -> 189.39394 | N29: =IFERROR(INDEX(CENTRE_TEST!$L:$L,MATCH(P29,CENTRE_TEST!$M:$M,0)),0) -> 0.24666667 | O29: =IFERROR( M29 * (N29/60) * (PARAMS!$B$5 / 100), 0) -> 0.77861953 | P29: =UPPER(TRIM(SUBSTITUTE(SUBSTITUTE(E29,CHAR(10)," "),CHAR(13)," "))) -> AFFECTATION GUICHET
A30: 4994 | B30: 31 | C30: 8286 | D30: Agent opération | E30: Remise avisés au guichet | F30: Colis | G30: =IFERROR(INDEX(code!$B$10:$B$13, MATCH(CENTRE_TEST!$E$28, code!$A$10:$A$13, 0)), "") -> ARRIVEE | H30: AMANA | I30: =CENTRE_TEST!$I$30 -> GLOBAL | J30: =UPPER(TRIM(SUBSTITUTE(G30," ",""))) & "|" & UPPER(TRIM(SUBSTITUTE(H30," ",""))) & "|" & UPPER(TRIM(SUBSTITUTE(I30," ",""))) -> ARRIVEE|AMANA|GLOBAL | K30: =IFERROR(SUMIFS(INPUT_VOLUMES!$D:$D,INPUT_VOLUMES!$A:$A,$G30,INPUT_VOLUMES!$B:$B,$H30,INPUT_VOLUMES!$C:$C,$I30),0) -> 50000 | L30: =K30/PARAMS!$B$2 -> 189.39394 | M30: =IF(F30="Sac", L30 / PARAMS!$B$6, L30 ) -> 189.39394 | N30: =IFERROR(INDEX(CENTRE_TEST!$L:$L,MATCH(P30,CENTRE_TEST!$M:$M,0)),0) -> 0.02 | O30: =IFERROR( M30 * (N30/60) * (PARAMS!$B$5 / 100), 0) -> 0.063131313 | P30: =UPPER(TRIM(SUBSTITUTE(SUBSTITUTE(E30,CHAR(10)," "),CHAR(13)," "))) -> REMISE AVISÉS AU GUICHET
A31: 4995 | B31: 32 | C31: 8286 | D31: Agent opération | E31: Préparatin fichier excel | F31: Colis | G31: =IFERROR(INDEX(code!$B$10:$B$13, MATCH(CENTRE_TEST!$E$28, code!$A$10:$A$13, 0)), "") -> ARRIVEE | H31: AMANA | I31: =CENTRE_TEST!$I$31 -> GLOBAL | J31: =UPPER(TRIM(SUBSTITUTE(G31," ",""))) & "|" & UPPER(TRIM(SUBSTITUTE(H31," ",""))) & "|" & UPPER(TRIM(SUBSTITUTE(I31," ",""))) -> ARRIVEE|AMANA|GLOBAL | K31: =IFERROR(SUMIFS(INPUT_VOLUMES!$D:$D,INPUT_VOLUMES!$A:$A,$G31,INPUT_VOLUMES!$B:$B,$H31,INPUT_VOLUMES!$C:$C,$I31),0) -> 50000 | L31: =K31/PARAMS!$B$2 -> 189.39394 | M31: =IF(F31="Sac", L31 / PARAMS!$B$6, L31 ) -> 189.39394 | N31: =IFERROR(INDEX(CENTRE_TEST!$L:$L,MATCH(P31,CENTRE_TEST!$M:$M,0)),0) -> 0.4 | O31: =IFERROR( M31 * (N31/60) * (PARAMS!$B$5 / 100), 0) -> 1.2626263 | P31: =UPPER(TRIM(SUBSTITUTE(SUBSTITUTE(E31,CHAR(10)," "),CHAR(13)," "))) -> PRÉPARATIN FICHIER EXCEL
A32: 4996 | B32: 33 | C32: 8286 | D32: Agent opération | E32: Scan et édition DNL | F32: Colis | G32: =IFERROR(INDEX(code!$B$10:$B$13, MATCH(CENTRE_TEST!$E$28, code!$A$10:$A$13, 0)), "") -> ARRIVEE | H32: AMANA | I32: =CENTRE_TEST!$I$32 -> GLOBAL | J32: =UPPER(TRIM(SUBSTITUTE(G32," ",""))) & "|" & UPPER(TRIM(SUBSTITUTE(H32," ",""))) & "|" & UPPER(TRIM(SUBSTITUTE(I32," ",""))) -> ARRIVEE|AMANA|GLOBAL | K32: =IFERROR(SUMIFS(INPUT_VOLUMES!$D:$D,INPUT_VOLUMES!$A:$A,$G32,INPUT_VOLUMES!$B:$B,$H32,INPUT_VOLUMES!$C:$C,$I32),0) -> 50000 | L32: =K32/PARAMS!$B$2 -> 189.39394 | M32: =IF(F32="Sac", L32 / PARAMS!$B$6, L32 ) -> 189.39394 | N32: =IFERROR(INDEX(CENTRE_TEST!$L:$L,MATCH(P32,CENTRE_TEST!$M:$M,0)),0) -> 0.005 | O32: =IFERROR( M32 * (N32/60) * (PARAMS!$B$5 / 100), 0) -> 0.015782828 | P32: =UPPER(TRIM(SUBSTITUTE(SUBSTITUTE(E32,CHAR(10)," "),CHAR(13)," "))) -> SCAN ET ÉDITION DNL
A33: 4997 | B33: 34 | C33: 8286 | D33: Agent opération | E33: Etat Levée | F33: Colis | G33: =IFERROR(INDEX(code!$B$10:$B$13, MATCH(CENTRE_TEST!$E$28, code!$A$10:$A$13, 0)), "") -> ARRIVEE | H33: AMANA | I33: =CENTRE_TEST!$I$33 -> GLOBAL | J33: =UPPER(TRIM(SUBSTITUTE(G33," ",""))) & "|" & UPPER(TRIM(SUBSTITUTE(H33," ",""))) & "|" & UPPER(TRIM(SUBSTITUTE(I33," ",""))) -> ARRIVEE|AMANA|GLOBAL | K33: =IFERROR(SUMIFS(INPUT_VOLUMES!$D:$D,INPUT_VOLUMES!$A:$A,$G33,INPUT_VOLUMES!$B:$B,$H33,INPUT_VOLUMES!$C:$C,$I33),0) -> 50000 | L33: =K33/PARAMS!$B$2 -> 189.39394 | M33: =IF(F33="Sac", L33 / PARAMS!$B$6, L33 ) -> 189.39394 | N33: =IFERROR(INDEX(CENTRE_TEST!$L:$L,MATCH(P33,CENTRE_TEST!$M:$M,0)),0) -> 0.01 | O33: =IFERROR( M33 * (N33/60) * (PARAMS!$B$5 / 100), 0) -> 0.031565657 | P33: =UPPER(TRIM(SUBSTITUTE(SUBSTITUTE(E33,CHAR(10)," "),CHAR(13)," "))) -> ETAT LEVÉE
A34: 4998 | B34: 35 | C34: 8286 | D34: Agent opération | E34: Récupération Physique colis | F34: Colis | G34: =IFERROR(INDEX(code!$B$10:$B$13, MATCH(CENTRE_TEST!$E$28, code!$A$10:$A$13, 0)), "") -> ARRIVEE | H34: AMANA | I34: =CENTRE_TEST!$I$34 -> GLOBAL | J34: =UPPER(TRIM(SUBSTITUTE(G34," ",""))) & "|" & UPPER(TRIM(SUBSTITUTE(H34," ",""))) & "|" & UPPER(TRIM(SUBSTITUTE(I34," ",""))) -> ARRIVEE|AMANA|GLOBAL | K34: =IFERROR(SUMIFS(INPUT_VOLUMES!$D:$D,INPUT_VOLUMES!$A:$A,$G34,INPUT_VOLUMES!$B:$B,$H34,INPUT_VOLUMES!$C:$C,$I34),0) -> 50000 | L34: =K34/PARAMS!$B$2 -> 189.39394 | M34: =IF(F34="Sac", L34 / PARAMS!$B$6, L34 ) -> 189.39394 | N34: =IFERROR(INDEX(CENTRE_TEST!$L:$L,MATCH(P34,CENTRE_TEST!$M:$M,0)),0) -> 0.35666667 | O34: =IFERROR( M34 * (N34/60) * (PARAMS!$B$5 / 100), 0) -> 1.1258418 | P34: =UPPER(TRIM(SUBSTITUTE(SUBSTITUTE(E34,CHAR(10)," "),CHAR(13)," "))) -> RÉCUPÉRATION PHYSIQUE COLIS
A35: 4999 | B35: 36 | C35: 8286 | D35: Agent opération | E35: Passation Vs Guichet | F35: Colis | G35: =IFERROR(INDEX(code!$B$10:$B$13, MATCH(CENTRE_TEST!$E$28, code!$A$10:$A$13, 0)), "") -> ARRIVEE | H35: AMANA | I35: =CENTRE_TEST!$I$35 -> GLOBAL | J35: =UPPER(TRIM(SUBSTITUTE(G35," ",""))) & "|" & UPPER(TRIM(SUBSTITUTE(H35," ",""))) & "|" & UPPER(TRIM(SUBSTITUTE(I35," ",""))) -> ARRIVEE|AMANA|GLOBAL | K35: =IFERROR(SUMIFS(INPUT_VOLUMES!$D:$D,INPUT_VOLUMES!$A:$A,$G35,INPUT_VOLUMES!$B:$B,$H35,INPUT_VOLUMES!$C:$C,$I35),0) -> 50000 | L35: =K35/PARAMS!$B$2 -> 189.39394 | M35: =IF(F35="Sac", L35 / PARAMS!$B$6, L35 ) -> 189.39394 | N35: =IFERROR(INDEX(CENTRE_TEST!$L:$L,MATCH(P35,CENTRE_TEST!$M:$M,0)),0) -> NULL | O35: =IFERROR( M35 * (N35/60) * (PARAMS!$B$5 / 100), 0) -> 0 | P35: =UPPER(TRIM(SUBSTITUTE(SUBSTITUTE(E35,CHAR(10)," "),CHAR(13)," "))) -> PASSATION VS GUICHET
A36: 5000 | B36: 37 | C36: 8286 | D36: Agent opération | E36: Réception | F36: Colis | G36: =IFERROR(INDEX(code!$B$10:$B$13, MATCH(CENTRE_TEST!$E$28, code!$A$10:$A$13, 0)), "") -> ARRIVEE | H36: AMANA | I36: =CENTRE_TEST!$I$36 -> GLOBAL | J36: =UPPER(TRIM(SUBSTITUTE(G36," ",""))) & "|" & UPPER(TRIM(SUBSTITUTE(H36," ",""))) & "|" & UPPER(TRIM(SUBSTITUTE(I36," ",""))) -> ARRIVEE|AMANA|GLOBAL | K36: =IFERROR(SUMIFS(INPUT_VOLUMES!$D:$D,INPUT_VOLUMES!$A:$A,$G36,INPUT_VOLUMES!$B:$B,$H36,INPUT_VOLUMES!$C:$C,$I36),0) -> 50000 | L36: =K36/PARAMS!$B$2 -> 189.39394 | M36: =IF(F36="Sac", L36 / PARAMS!$B$6, L36 ) -> 189.39394 | N36: =IFERROR(INDEX(CENTRE_TEST!$L:$L,MATCH(P36,CENTRE_TEST!$M:$M,0)),0) -> 0.16 | O36: =IFERROR( M36 * (N36/60) * (PARAMS!$B$5 / 100), 0) -> 0.50505051 | P36: =UPPER(TRIM(SUBSTITUTE(SUBSTITUTE(E36,CHAR(10)," "),CHAR(13)," "))) -> RÉCEPTION
A37: 5001 | B37: 38 | C37: 8286 | D37: Agent opération | E37: Numérotage | F37: Colis | G37: =IFERROR(INDEX(code!$B$10:$B$13, MATCH(CENTRE_TEST!$E$28, code!$A$10:$A$13, 0)), "") -> ARRIVEE | H37: AMANA | I37: =CENTRE_TEST!$I$37 -> GLOBAL | J37: =UPPER(TRIM(SUBSTITUTE(G37," ",""))) & "|" & UPPER(TRIM(SUBSTITUTE(H37," ",""))) & "|" & UPPER(TRIM(SUBSTITUTE(I37," ",""))) -> ARRIVEE|AMANA|GLOBAL | K37: =IFERROR(SUMIFS(INPUT_VOLUMES!$D:$D,INPUT_VOLUMES!$A:$A,$G37,INPUT_VOLUMES!$B:$B,$H37,INPUT_VOLUMES!$C:$C,$I37),0) -> 50000 | L37: =K37/PARAMS!$B$2 -> 189.39394 | M37: =IF(F37="Sac", L37 / PARAMS!$B$6, L37 ) -> 189.39394 | N37: =IFERROR(INDEX(CENTRE_TEST!$L:$L,MATCH(P37,CENTRE_TEST!$M:$M,0)),0) -> NULL | O37: =IFERROR( M37 * (N37/60) * (PARAMS!$B$5 / 100), 0) -> 0 | P37: =UPPER(TRIM(SUBSTITUTE(SUBSTITUTE(E37,CHAR(10)," "),CHAR(13)," "))) -> NUMÉROTAGE
A38: 5002 | B38: 39 | C38: 8286 | D38: Agent opération | E38: Mise en sac | F38: Colis | G38: =IFERROR(INDEX(code!$B$10:$B$13, MATCH(CENTRE_TEST!$E$28, code!$A$10:$A$13, 0)), "") -> ARRIVEE | H38: AMANA | I38: =CENTRE_TEST!$I$38 -> GLOBAL | J38: =UPPER(TRIM(SUBSTITUTE(G38," ",""))) & "|" & UPPER(TRIM(SUBSTITUTE(H38," ",""))) & "|" & UPPER(TRIM(SUBSTITUTE(I38," ",""))) -> ARRIVEE|AMANA|GLOBAL | K38: =IFERROR(SUMIFS(INPUT_VOLUMES!$D:$D,INPUT_VOLUMES!$A:$A,$G38,INPUT_VOLUMES!$B:$B,$H38,INPUT_VOLUMES!$C:$C,$I38),0) -> 50000 | L38: =K38/PARAMS!$B$2 -> 189.39394 | M38: =IF(F38="Sac", L38 / PARAMS!$B$6, L38 ) -> 189.39394 | N38: =IFERROR(INDEX(CENTRE_TEST!$L:$L,MATCH(P38,CENTRE_TEST!$M:$M,0)),0) -> 0.19833333 | O38: =IFERROR( M38 * (N38/60) * (PARAMS!$B$5 / 100), 0) -> 0.62605219 | P38: =UPPER(TRIM(SUBSTITUTE(SUBSTITUTE(E38,CHAR(10)," "),CHAR(13)," "))) -> MISE EN SAC
A39: 5003 | B39: 40 | C39: 8286 | D39: Agent opération | E39: Expédition | F39: Colis | G39: =IFERROR(INDEX(code!$B$10:$B$13, MATCH(CENTRE_TEST!$E$28, code!$A$10:$A$13, 0)), "") -> ARRIVEE | H39: AMANA | I39: =CENTRE_TEST!$I$39 -> GLOBAL | J39: =UPPER(TRIM(SUBSTITUTE(G39," ",""))) & "|" & UPPER(TRIM(SUBSTITUTE(H39," ",""))) & "|" & UPPER(TRIM(SUBSTITUTE(I39," ",""))) -> ARRIVEE|AMANA|GLOBAL | K39: =IFERROR(SUMIFS(INPUT_VOLUMES!$D:$D,INPUT_VOLUMES!$A:$A,$G39,INPUT_VOLUMES!$B:$B,$H39,INPUT_VOLUMES!$C:$C,$I39),0) -> 50000 | L39: =K39/PARAMS!$B$2 -> 189.39394 | M39: =IF(F39="Sac", L39 / PARAMS!$B$6, L39 ) -> 189.39394 | N39: =IFERROR(INDEX(CENTRE_TEST!$L:$L,MATCH(P39,CENTRE_TEST!$M:$M,0)),0) -> 0.205 | O39: =IFERROR( M39 * (N39/60) * (PARAMS!$B$5 / 100), 0) -> 0.64709596 | P39: =UPPER(TRIM(SUBSTITUTE(SUBSTITUTE(E39,CHAR(10)," "),CHAR(13)," "))) -> EXPÉDITION
A40: 5004 | B40: 41 | C40: 8286 | D40: Agent opération | E40: classement en cabine instance | F40: Colis | G40: =IFERROR(INDEX(code!$B$10:$B$13, MATCH(CENTRE_TEST!$E$28, code!$A$10:$A$13, 0)), "") -> ARRIVEE | H40: AMANA | I40: =CENTRE_TEST!$I$40 -> GLOBAL | J40: =UPPER(TRIM(SUBSTITUTE(G40," ",""))) & "|" & UPPER(TRIM(SUBSTITUTE(H40," ",""))) & "|" & UPPER(TRIM(SUBSTITUTE(I40," ",""))) -> ARRIVEE|AMANA|GLOBAL | K40: =IFERROR(SUMIFS(INPUT_VOLUMES!$D:$D,INPUT_VOLUMES!$A:$A,$G40,INPUT_VOLUMES!$B:$B,$H40,INPUT_VOLUMES!$C:$C,$I40),0) -> 50000 | L40: =K40/PARAMS!$B$2 -> 189.39394 | M40: =IF(F40="Sac", L40 / PARAMS!$B$6, L40 ) -> 189.39394 | N40: =IFERROR(INDEX(CENTRE_TEST!$L:$L,MATCH(P40,CENTRE_TEST!$M:$M,0)),0) -> 0.21666667 | O40: =IFERROR( M40 * (N40/60) * (PARAMS!$B$5 / 100), 0) -> 0.68392256 | P40: =UPPER(TRIM(SUBSTITUTE(SUBSTITUTE(E40,CHAR(10)," "),CHAR(13)," "))) -> CLASSEMENT EN CABINE INSTANCE
A41: 5005 | B41: 42 | C41: 8286 | D41: Agent opération | E41: contrôle physique | F41: Colis | G41: =IFERROR(INDEX(code!$B$10:$B$13, MATCH(CENTRE_TEST!$E$28, code!$A$10:$A$13, 0)), "") -> ARRIVEE | H41: AMANA | I41: =CENTRE_TEST!$I$41 -> GLOBAL | J41: =UPPER(TRIM(SUBSTITUTE(G41," ",""))) & "|" & UPPER(TRIM(SUBSTITUTE(H41," ",""))) & "|" & UPPER(TRIM(SUBSTITUTE(I41," ",""))) -> ARRIVEE|AMANA|GLOBAL | K41: =IFERROR(SUMIFS(INPUT_VOLUMES!$D:$D,INPUT_VOLUMES!$A:$A,$G41,INPUT_VOLUMES!$B:$B,$H41,INPUT_VOLUMES!$C:$C,$I41),0) -> 50000 | L41: =K41/PARAMS!$B$2 -> 189.39394 | M41: =IF(F41="Sac", L41 / PARAMS!$B$6, L41 ) -> 189.39394 | N41: =IFERROR(INDEX(CENTRE_TEST!$L:$L,MATCH(P41,CENTRE_TEST!$M:$M,0)),0) -> 0.4 | O41: =IFERROR( M41 * (N41/60) * (PARAMS!$B$5 / 100), 0) -> 1.2626263 | P41: =UPPER(TRIM(SUBSTITUTE(SUBSTITUTE(E41,CHAR(10)," "),CHAR(13)," "))) -> CONTRÔLE PHYSIQUE
A42: 5006 | B42: 43 | C42: 8286 | D42: Agent opération | E42: création dépeche | F42: Colis | G42: =IFERROR(INDEX(code!$B$10:$B$13, MATCH(CENTRE_TEST!$E$28, code!$A$10:$A$13, 0)), "") -> ARRIVEE | H42: AMANA | I42: =CENTRE_TEST!$I$42 -> GLOBAL | J42: =UPPER(TRIM(SUBSTITUTE(G42," ",""))) & "|" & UPPER(TRIM(SUBSTITUTE(H42," ",""))) & "|" & UPPER(TRIM(SUBSTITUTE(I42," ",""))) -> ARRIVEE|AMANA|GLOBAL | K42: =IFERROR(SUMIFS(INPUT_VOLUMES!$D:$D,INPUT_VOLUMES!$A:$A,$G42,INPUT_VOLUMES!$B:$B,$H42,INPUT_VOLUMES!$C:$C,$I42),0) -> 50000 | L42: =K42/PARAMS!$B$2 -> 189.39394 | M42: =IF(F42="Sac", L42 / PARAMS!$B$6, L42 ) -> 189.39394 | N42: =IFERROR(INDEX(CENTRE_TEST!$L:$L,MATCH(P42,CENTRE_TEST!$M:$M,0)),0) -> 0.17666667 | O42: =IFERROR( M42 * (N42/60) * (PARAMS!$B$5 / 100), 0) -> 0.55765993 | P42: =UPPER(TRIM(SUBSTITUTE(SUBSTITUTE(E42,CHAR(10)," "),CHAR(13)," "))) -> CRÉATION DÉPECHE
A43: 5007 | B43: 45 | C43: 8286 | D43: Agent opération | E43: Edition PART | F43: Colis | G43: =IFERROR(INDEX(code!$B$10:$B$13, MATCH(CENTRE_TEST!$E$28, code!$A$10:$A$13, 0)), "") -> ARRIVEE | H43: AMANA | I43: =CENTRE_TEST!$I$43 -> GLOBAL | J43: =UPPER(TRIM(SUBSTITUTE(G43," ",""))) & "|" & UPPER(TRIM(SUBSTITUTE(H43," ",""))) & "|" & UPPER(TRIM(SUBSTITUTE(I43," ",""))) -> ARRIVEE|AMANA|GLOBAL | K43: =IFERROR(SUMIFS(INPUT_VOLUMES!$D:$D,INPUT_VOLUMES!$A:$A,$G43,INPUT_VOLUMES!$B:$B,$H43,INPUT_VOLUMES!$C:$C,$I43),0) -> 50000 | L43: =K43/PARAMS!$B$2 -> 189.39394 | M43: =IF(F43="Sac", L43 / PARAMS!$B$6, L43 ) -> 189.39394 | N43: =IFERROR(INDEX(CENTRE_TEST!$L:$L,MATCH(P43,CENTRE_TEST!$M:$M,0)),0) -> 0.19 | O43: =IFERROR( M43 * (N43/60) * (PARAMS!$B$5 / 100), 0) -> 0.59974747 | P43: =UPPER(TRIM(SUBSTITUTE(SUBSTITUTE(E43,CHAR(10)," "),CHAR(13)," "))) -> EDITION PART
A44: 5008 | B44: 46 | C44: 8286 | D44: Agent opération | E44: fermeture sac | F44: Sac | G44: =IFERROR(INDEX(code!$B$10:$B$13, MATCH(CENTRE_TEST!$E$28, code!$A$10:$A$13, 0)), "") -> ARRIVEE | H44: AMANA | I44: =CENTRE_TEST!$I$44 -> GLOBAL | J44: =UPPER(TRIM(SUBSTITUTE(G44," ",""))) & "|" & UPPER(TRIM(SUBSTITUTE(H44," ",""))) & "|" & UPPER(TRIM(SUBSTITUTE(I44," ",""))) -> ARRIVEE|AMANA|GLOBAL | K44: =IFERROR(SUMIFS(INPUT_VOLUMES!$D:$D,INPUT_VOLUMES!$A:$A,$G44,INPUT_VOLUMES!$B:$B,$H44,INPUT_VOLUMES!$C:$C,$I44),0) -> 50000 | L44: =K44/PARAMS!$B$2 -> 189.39394 | M44: =IF(F44="Sac", L44 / PARAMS!$B$6, L44 ) -> 37.878788 | N44: =IFERROR(INDEX(CENTRE_TEST!$L:$L,MATCH(P44,CENTRE_TEST!$M:$M,0)),0) -> 0.18 | O44: =IFERROR( M44 * (N44/60) * (PARAMS!$B$5 / 100), 0) -> 0.11363636 | P44: =UPPER(TRIM(SUBSTITUTE(SUBSTITUTE(E44,CHAR(10)," "),CHAR(13)," "))) -> FERMETURE SAC
A45: 5009 | B45: 47 | C45: 8286 | D45: Agent opération | E45: Chargement Camion Colis | F45: Colis | G45: =IFERROR(INDEX(code!$B$10:$B$13, MATCH(CENTRE_TEST!$E$28, code!$A$10:$A$13, 0)), "") -> ARRIVEE | H45: AMANA | I45: =CENTRE_TEST!$I$45 -> GLOBAL | J45: =UPPER(TRIM(SUBSTITUTE(G45," ",""))) & "|" & UPPER(TRIM(SUBSTITUTE(H45," ",""))) & "|" & UPPER(TRIM(SUBSTITUTE(I45," ",""))) -> ARRIVEE|AMANA|GLOBAL | K45: =IFERROR(SUMIFS(INPUT_VOLUMES!$D:$D,INPUT_VOLUMES!$A:$A,$G45,INPUT_VOLUMES!$B:$B,$H45,INPUT_VOLUMES!$C:$C,$I45),0) -> 50000 | L45: =K45/PARAMS!$B$2 -> 189.39394 | M45: =IF(F45="Sac", L45 / PARAMS!$B$6, L45 ) -> 189.39394 | N45: =IFERROR(INDEX(CENTRE_TEST!$L:$L,MATCH(P45,CENTRE_TEST!$M:$M,0)),0) -> 0.35833333 | O45: =IFERROR( M45 * (N45/60) * (PARAMS!$B$5 / 100), 0) -> 1.1311027 | P45: =UPPER(TRIM(SUBSTITUTE(SUBSTITUTE(E45,CHAR(10)," "),CHAR(13)," "))) -> CHARGEMENT CAMION COLIS
A46: 5010 | B46: 48 | C46: 8286 | D46: Agent opération | E46: Chargement Camion Sac | F46: Sac | G46: =IFERROR(INDEX(code!$B$10:$B$13, MATCH(CENTRE_TEST!$E$28, code!$A$10:$A$13, 0)), "") -> ARRIVEE | H46: AMANA | I46: =CENTRE_TEST!$I$46 -> GLOBAL | J46: =UPPER(TRIM(SUBSTITUTE(G46," ",""))) & "|" & UPPER(TRIM(SUBSTITUTE(H46," ",""))) & "|" & UPPER(TRIM(SUBSTITUTE(I46," ",""))) -> ARRIVEE|AMANA|GLOBAL | K46: =IFERROR(SUMIFS(INPUT_VOLUMES!$D:$D,INPUT_VOLUMES!$A:$A,$G46,INPUT_VOLUMES!$B:$B,$H46,INPUT_VOLUMES!$C:$C,$I46),0) -> 50000 | L46: =K46/PARAMS!$B$2 -> 189.39394 | M46: =IF(F46="Sac", L46 / PARAMS!$B$6, L46 ) -> 37.878788 | N46: =IFERROR(INDEX(CENTRE_TEST!$L:$L,MATCH(P46,CENTRE_TEST!$M:$M,0)),0) -> 0.22833333 | O46: =IFERROR( M46 * (N46/60) * (PARAMS!$B$5 / 100), 0) -> 0.14414983 | P46: =UPPER(TRIM(SUBSTITUTE(SUBSTITUTE(E46,CHAR(10)," "),CHAR(13)," "))) -> CHARGEMENT CAMION SAC
A47: 5011 | B47: 49 | C47: 8286 | D47: Agent opération | E47: Réception courrier avisé sur SI COM | F47: Courrier | G47: =IFERROR(INDEX(code!$B$10:$B$13, MATCH(CENTRE_TEST!$E$28, code!$A$10:$A$13, 0)), "") -> ARRIVEE | H47: CO | I47: =CENTRE_TEST!$I$47 -> GLOBAL | J47: =UPPER(TRIM(SUBSTITUTE(G47," ",""))) & "|" & UPPER(TRIM(SUBSTITUTE(H47," ",""))) & "|" & UPPER(TRIM(SUBSTITUTE(I47," ",""))) -> ARRIVEE|CO|GLOBAL | K47: =IFERROR(SUMIFS(INPUT_VOLUMES!$D:$D,INPUT_VOLUMES!$A:$A,$G47,INPUT_VOLUMES!$B:$B,$H47,INPUT_VOLUMES!$C:$C,$I47),0) -> 6000 | L47: =K47/PARAMS!$B$2 -> 22.727273 | M47: =IF(F47="Sac", L47 / PARAMS!$B$6, L47 ) -> 22.727273 | N47: =IFERROR(INDEX(CENTRE_TEST!$L:$L,MATCH(P47,CENTRE_TEST!$M:$M,0)),0) -> NULL | O47: =IFERROR( M47 * (N47/60) * (PARAMS!$B$5 / 100), 0) -> 0 | P47: =UPPER(TRIM(SUBSTITUTE(SUBSTITUTE(E47,CHAR(10)," "),CHAR(13)," "))) -> RÉCEPTION COURRIER AVISÉ SUR SI COM
A48: 5012 | B48: 50 | C48: 8286 | D48: Agent opération | E48: Affectation : Avisé, Abonné, Vaguemaster … | F48: Courrier Recommandé | G48: =IFERROR(INDEX(code!$B$10:$B$13, MATCH(CENTRE_TEST!$E$28, code!$A$10:$A$13, 0)), "") -> ARRIVEE | H48: CR | I48: =CENTRE_TEST!$I$48 -> GLOBAL | J48: =UPPER(TRIM(SUBSTITUTE(G48," ",""))) & "|" & UPPER(TRIM(SUBSTITUTE(H48," ",""))) & "|" & UPPER(TRIM(SUBSTITUTE(I48," ",""))) -> ARRIVEE|CR|GLOBAL | K48: =IFERROR(SUMIFS(INPUT_VOLUMES!$D:$D,INPUT_VOLUMES!$A:$A,$G48,INPUT_VOLUMES!$B:$B,$H48,INPUT_VOLUMES!$C:$C,$I48),0) -> 0 | L48: =K48/PARAMS!$B$2 -> 0 | M48: =IF(F48="Sac", L48 / PARAMS!$B$6, L48 ) -> 0 | N48: =IFERROR(INDEX(CENTRE_TEST!$L:$L,MATCH(P48,CENTRE_TEST!$M:$M,0)),0) -> 0.43333333 | O48: =IFERROR( M48 * (N48/60) * (PARAMS!$B$5 / 100), 0) -> 0 | P48: =UPPER(TRIM(SUBSTITUTE(SUBSTITUTE(E48,CHAR(10)," "),CHAR(13)," "))) -> AFFECTATION : AVISÉ, ABONNÉ, VAGUEMASTER …
A49: 5013 | B49: 51 | C49: 8286 | D49: Agent opération | E49: Notification envoi avisé client boite postale | F49: Courrier | G49: =IFERROR(INDEX(code!$B$10:$B$13, MATCH(CENTRE_TEST!$E$28, code!$A$10:$A$13, 0)), "") -> ARRIVEE | H49: CO | I49: =CENTRE_TEST!$I$49 -> GLOBAL | J49: =UPPER(TRIM(SUBSTITUTE(G49," ",""))) & "|" & UPPER(TRIM(SUBSTITUTE(H49," ",""))) & "|" & UPPER(TRIM(SUBSTITUTE(I49," ",""))) -> ARRIVEE|CO|GLOBAL | K49: =IFERROR(SUMIFS(INPUT_VOLUMES!$D:$D,INPUT_VOLUMES!$A:$A,$G49,INPUT_VOLUMES!$B:$B,$H49,INPUT_VOLUMES!$C:$C,$I49),0) -> 6000 | L49: =K49/PARAMS!$B$2 -> 22.727273 | M49: =IF(F49="Sac", L49 / PARAMS!$B$6, L49 ) -> 22.727273 | N49: =IFERROR(INDEX(CENTRE_TEST!$L:$L,MATCH(P49,CENTRE_TEST!$M:$M,0)),0) -> 0.038333333 | O49: =IFERROR( M49 * (N49/60) * (PARAMS!$B$5 / 100), 0) -> 0.014520202 | P49: =UPPER(TRIM(SUBSTITUTE(SUBSTITUTE(E49,CHAR(10)," "),CHAR(13)," "))) -> NOTIFICATION ENVOI AVISÉ CLIENT BOITE POSTALE
A50: 5014 | B50: 53 | C50: 8286 | D50: Agent opération | E50: Déchargement VAN | F50: Sac | G50: =IFERROR(INDEX(code!$B$10:$B$13, MATCH(CENTRE_TEST!$E$28, code!$A$10:$A$13, 0)), "") -> ARRIVEE | H50: AMANA | I50: =CENTRE_TEST!$I$50 -> GLOBAL | J50: =UPPER(TRIM(SUBSTITUTE(G50," ",""))) & "|" & UPPER(TRIM(SUBSTITUTE(H50," ",""))) & "|" & UPPER(TRIM(SUBSTITUTE(I50," ",""))) -> ARRIVEE|AMANA|GLOBAL | K50: =IFERROR(SUMIFS(INPUT_VOLUMES!$D:$D,INPUT_VOLUMES!$A:$A,$G50,INPUT_VOLUMES!$B:$B,$H50,INPUT_VOLUMES!$C:$C,$I50),0) -> 50000 | L50: =K50/PARAMS!$B$2 -> 189.39394 | M50: =IF(F50="Sac", L50 / PARAMS!$B$6, L50 ) -> 37.878788 | N50: =IFERROR(INDEX(CENTRE_TEST!$L:$L,MATCH(P50,CENTRE_TEST!$M:$M,0)),0) -> 0.63333333 | O50: =IFERROR( M50 * (N50/60) * (PARAMS!$B$5 / 100), 0) -> 0.39983165 | P50: =UPPER(TRIM(SUBSTITUTE(SUBSTITUTE(E50,CHAR(10)," "),CHAR(13)," "))) -> DÉCHARGEMENT VAN
A51: 5015 | B51: 54 | C51: 8286 | D51: Agent opération | E51: Enregistrement sur PART 125 | F51: Sac | G51: =IFERROR(INDEX(code!$B$10:$B$13, MATCH(CENTRE_TEST!$E$28, code!$A$10:$A$13, 0)), "") -> ARRIVEE | H51: AMANA | I51: =CENTRE_TEST!$I$51 -> GLOBAL | J51: =UPPER(TRIM(SUBSTITUTE(G51," ",""))) & "|" & UPPER(TRIM(SUBSTITUTE(H51," ",""))) & "|" & UPPER(TRIM(SUBSTITUTE(I51," ",""))) -> ARRIVEE|AMANA|GLOBAL | K51: =IFERROR(SUMIFS(INPUT_VOLUMES!$D:$D,INPUT_VOLUMES!$A:$A,$G51,INPUT_VOLUMES!$B:$B,$H51,INPUT_VOLUMES!$C:$C,$I51),0) -> 50000 | L51: =K51/PARAMS!$B$2 -> 189.39394 | M51: =IF(F51="Sac", L51 / PARAMS!$B$6, L51 ) -> 37.878788 | N51: =IFERROR(INDEX(CENTRE_TEST!$L:$L,MATCH(P51,CENTRE_TEST!$M:$M,0)),0) -> 0.033333333 | O51: =IFERROR( M51 * (N51/60) * (PARAMS!$B$5 / 100), 0) -> 0.021043771 | P51: =UPPER(TRIM(SUBSTITUTE(SUBSTITUTE(E51,CHAR(10)," "),CHAR(13)," "))) -> ENREGISTREMENT SUR PART 125
A52: 5016 | B52: 55 | C52: 8286 | D52: Agent opération | E52: Ouverture sac | F52: Sac | G52: =IFERROR(INDEX(code!$B$10:$B$13, MATCH(CENTRE_TEST!$E$28, code!$A$10:$A$13, 0)), "") -> ARRIVEE | H52: AMANA | I52: =CENTRE_TEST!$I$52 -> GLOBAL | J52: =UPPER(TRIM(SUBSTITUTE(G52," ",""))) & "|" & UPPER(TRIM(SUBSTITUTE(H52," ",""))) & "|" & UPPER(TRIM(SUBSTITUTE(I52," ",""))) -> ARRIVEE|AMANA|GLOBAL | K52: =IFERROR(SUMIFS(INPUT_VOLUMES!$D:$D,INPUT_VOLUMES!$A:$A,$G52,INPUT_VOLUMES!$B:$B,$H52,INPUT_VOLUMES!$C:$C,$I52),0) -> 50000 | L52: =K52/PARAMS!$B$2 -> 189.39394 | M52: =IF(F52="Sac", L52 / PARAMS!$B$6, L52 ) -> 37.878788 | N52: 4 | O52: =IFERROR( M52 * (N52/60) * (PARAMS!$B$5 / 100), 0) -> 2.5252525 | P52: =UPPER(TRIM(SUBSTITUTE(SUBSTITUTE(E52,CHAR(10)," "),CHAR(13)," "))) -> OUVERTURE SAC
A53: 5017 | B53: 56 | C53: 8286 | D53: Agent opération | E53: Scan & Réception SI | F53: Courrier Recommandé | G53: =IFERROR(INDEX(code!$B$10:$B$13, MATCH(CENTRE_TEST!$E$28, code!$A$10:$A$13, 0)), "") -> ARRIVEE | H53: CR | I53: =CENTRE_TEST!$I$53 -> GLOBAL | J53: =UPPER(TRIM(SUBSTITUTE(G53," ",""))) & "|" & UPPER(TRIM(SUBSTITUTE(H53," ",""))) & "|" & UPPER(TRIM(SUBSTITUTE(I53," ",""))) -> ARRIVEE|CR|GLOBAL | K53: =IFERROR(SUMIFS(INPUT_VOLUMES!$D:$D,INPUT_VOLUMES!$A:$A,$G53,INPUT_VOLUMES!$B:$B,$H53,INPUT_VOLUMES!$C:$C,$I53),0) -> 0 | L53: =K53/PARAMS!$B$2 -> 0 | M53: =IF(F53="Sac", L53 / PARAMS!$B$6, L53 ) -> 0 | N53: =IFERROR(INDEX(CENTRE_TEST!$L:$L,MATCH(P53,CENTRE_TEST!$M:$M,0)),0) -> 0.033333333 | O53: =IFERROR( M53 * (N53/60) * (PARAMS!$B$5 / 100), 0) -> 0 | P53: =UPPER(TRIM(SUBSTITUTE(SUBSTITUTE(E53,CHAR(10)," "),CHAR(13)," "))) -> SCAN & RÉCEPTION SI
A54: 5018 | B54: 57 | C54: 8286 | D54: Agent opération | E54: Affectation au guichet | F54: Courrier Recommandé | G54: =IFERROR(INDEX(code!$B$10:$B$13, MATCH(CENTRE_TEST!$E$28, code!$A$10:$A$13, 0)), "") -> ARRIVEE | H54: CR | I54: =CENTRE_TEST!$I$54 -> GLOBAL | J54: =UPPER(TRIM(SUBSTITUTE(G54," ",""))) & "|" & UPPER(TRIM(SUBSTITUTE(H54," ",""))) & "|" & UPPER(TRIM(SUBSTITUTE(I54," ",""))) -> ARRIVEE|CR|GLOBAL | K54: =IFERROR(SUMIFS(INPUT_VOLUMES!$D:$D,INPUT_VOLUMES!$A:$A,$G54,INPUT_VOLUMES!$B:$B,$H54,INPUT_VOLUMES!$C:$C,$I54),0) -> 0 | L54: =K54/PARAMS!$B$2 -> 0 | M54: =IF(F54="Sac", L54 / PARAMS!$B$6, L54 ) -> 0 | N54: =IFERROR(INDEX(CENTRE_TEST!$L:$L,MATCH(P54,CENTRE_TEST!$M:$M,0)),0) -> 0.43333333 | O54: =IFERROR( M54 * (N54/60) * (PARAMS!$B$5 / 100), 0) -> 0 | P54: =UPPER(TRIM(SUBSTITUTE(SUBSTITUTE(E54,CHAR(10)," "),CHAR(13)," "))) -> AFFECTATION AU GUICHET
A55: 5019 | B55: 58 | C55: 8286 | D55: Agent opération | E55: Scan et édition DNL | F55: Courrier Recommandé | G55: =IFERROR(INDEX(code!$B$10:$B$13, MATCH(CENTRE_TEST!$E$28, code!$A$10:$A$13, 0)), "") -> ARRIVEE | H55: CR | I55: =CENTRE_TEST!$I$55 -> GLOBAL | J55: =UPPER(TRIM(SUBSTITUTE(G55," ",""))) & "|" & UPPER(TRIM(SUBSTITUTE(H55," ",""))) & "|" & UPPER(TRIM(SUBSTITUTE(I55," ",""))) -> ARRIVEE|CR|GLOBAL | K55: =IFERROR(SUMIFS(INPUT_VOLUMES!$D:$D,INPUT_VOLUMES!$A:$A,$G55,INPUT_VOLUMES!$B:$B,$H55,INPUT_VOLUMES!$C:$C,$I55),0) -> 0 | L55: =K55/PARAMS!$B$2 -> 0 | M55: =IF(F55="Sac", L55 / PARAMS!$B$6, L55 ) -> 0 | N55: =IFERROR(INDEX(CENTRE_TEST!$L:$L,MATCH(P55,CENTRE_TEST!$M:$M,0)),0) -> 0.005 | O55: =IFERROR( M55 * (N55/60) * (PARAMS!$B$5 / 100), 0) -> 0 | P55: =UPPER(TRIM(SUBSTITUTE(SUBSTITUTE(E55,CHAR(10)," "),CHAR(13)," "))) -> SCAN ET ÉDITION DNL
A56: 5020 | B56: 59 | C56: 8286 | D56: Agent opération | E56: Remise à l'agent Barid Pro | F56: Courrier Recommandé | G56: =IFERROR(INDEX(code!$B$10:$B$13, MATCH(CENTRE_TEST!$E$28, code!$A$10:$A$13, 0)), "") -> ARRIVEE | H56: CR | I56: =CENTRE_TEST!$I$56 -> GLOBAL | J56: =UPPER(TRIM(SUBSTITUTE(G56," ",""))) & "|" & UPPER(TRIM(SUBSTITUTE(H56," ",""))) & "|" & UPPER(TRIM(SUBSTITUTE(I56," ",""))) -> ARRIVEE|CR|GLOBAL | K56: =IFERROR(SUMIFS(INPUT_VOLUMES!$D:$D,INPUT_VOLUMES!$A:$A,$G56,INPUT_VOLUMES!$B:$B,$H56,INPUT_VOLUMES!$C:$C,$I56),0) -> 0 | L56: =K56/PARAMS!$B$2 -> 0 | M56: =IF(F56="Sac", L56 / PARAMS!$B$6, L56 ) -> 0 | N56: =IFERROR(INDEX(CENTRE_TEST!$L:$L,MATCH(P56,CENTRE_TEST!$M:$M,0)),0) -> NULL | O56: =IFERROR( M56 * (N56/60) * (PARAMS!$B$5 / 100), 0) -> 0 | P56: =UPPER(TRIM(SUBSTITUTE(SUBSTITUTE(E56,CHAR(10)," "),CHAR(13)," "))) -> REMISE À L'AGENT BARID PRO
A57: 5021 | B57: 60 | C57: 8286 | D57: Agent opération | E57: Préparatin fichier excel | F57: Courrier | G57: =IFERROR(INDEX(code!$B$10:$B$13, MATCH(CENTRE_TEST!$E$28, code!$A$10:$A$13, 0)), "") -> ARRIVEE | H57: CO | I57: =CENTRE_TEST!$I$57 -> GLOBAL | J57: =UPPER(TRIM(SUBSTITUTE(G57," ",""))) & "|" & UPPER(TRIM(SUBSTITUTE(H57," ",""))) & "|" & UPPER(TRIM(SUBSTITUTE(I57," ",""))) -> ARRIVEE|CO|GLOBAL | K57: =IFERROR(SUMIFS(INPUT_VOLUMES!$D:$D,INPUT_VOLUMES!$A:$A,$G57,INPUT_VOLUMES!$B:$B,$H57,INPUT_VOLUMES!$C:$C,$I57),0) -> 6000 | L57: =K57/PARAMS!$B$2 -> 22.727273 | M57: =IF(F57="Sac", L57 / PARAMS!$B$6, L57 ) -> 22.727273 | N57: =IFERROR(INDEX(CENTRE_TEST!$L:$L,MATCH(P57,CENTRE_TEST!$M:$M,0)),0) -> 0.4 | O57: =IFERROR( M57 * (N57/60) * (PARAMS!$B$5 / 100), 0) -> 0.15151515 | P57: =UPPER(TRIM(SUBSTITUTE(SUBSTITUTE(E57,CHAR(10)," "),CHAR(13)," "))) -> PRÉPARATIN FICHIER EXCEL
A58: 5022 | B58: 61 | C58: 8286 | D58: Agent opération | E58: Préparation & mise en sac | F58: Courrier | G58: =IFERROR(INDEX(code!$B$10:$B$13, MATCH(CENTRE_TEST!$E$28, code!$A$10:$A$13, 0)), "") -> ARRIVEE | H58: CO | I58: =CENTRE_TEST!$I$58 -> GLOBAL | J58: =UPPER(TRIM(SUBSTITUTE(G58," ",""))) & "|" & UPPER(TRIM(SUBSTITUTE(H58," ",""))) & "|" & UPPER(TRIM(SUBSTITUTE(I58," ",""))) -> ARRIVEE|CO|GLOBAL | K58: =IFERROR(SUMIFS(INPUT_VOLUMES!$D:$D,INPUT_VOLUMES!$A:$A,$G58,INPUT_VOLUMES!$B:$B,$H58,INPUT_VOLUMES!$C:$C,$I58),0) -> 6000 | L58: =K58/PARAMS!$B$2 -> 22.727273 | M58: =IF(F58="Sac", L58 / PARAMS!$B$6, L58 ) -> 22.727273 | N58: =IFERROR(INDEX(CENTRE_TEST!$L:$L,MATCH(P58,CENTRE_TEST!$M:$M,0)),0) -> 0.4 | O58: =IFERROR( M58 * (N58/60) * (PARAMS!$B$5 / 100), 0) -> 0.15151515 | P58: =UPPER(TRIM(SUBSTITUTE(SUBSTITUTE(E58,CHAR(10)," "),CHAR(13)," "))) -> PRÉPARATION & MISE EN SAC
A59: 5023 | B59: 62 | C59: 8286 | D59: Agent opération | E59: Remplissage Sac | F59: Sac | G59: =IFERROR(INDEX(code!$B$10:$B$13, MATCH(CENTRE_TEST!$E$52, code!$A$10:$A$13, 0)), "") -> ARRIVEE | H59: AMANA | I59: =CENTRE_TEST!$I$52 -> GLOBAL | J59: =UPPER(TRIM(SUBSTITUTE(G59," ",""))) & "|" & UPPER(TRIM(SUBSTITUTE(H59," ",""))) & "|" & UPPER(TRIM(SUBSTITUTE(I59," ",""))) -> ARRIVEE|AMANA|GLOBAL | K59: =IFERROR(SUMIFS(INPUT_VOLUMES!$D:$D,INPUT_VOLUMES!$A:$A,$G59,INPUT_VOLUMES!$B:$B,$H59,INPUT_VOLUMES!$C:$C,$I59),0) -> 50000 | L59: =K59/PARAMS!$B$2 -> 189.39394 | M59: =IF(F59="Sac", L59 / PARAMS!$B$6, L59 ) -> 37.878788 | N59: =IFERROR(INDEX(CENTRE_TEST!$L:$L,MATCH(P59,CENTRE_TEST!$M:$M,0)),0) -> 0.4 | O59: =IFERROR( M59 * (N59/60) * (PARAMS!$B$5 / 100), 0) -> 0.25252525 | P59: =UPPER(TRIM(SUBSTITUTE(SUBSTITUTE(E59,CHAR(10)," "),CHAR(13)," "))) -> REMPLISSAGE SAC
A60: 5024 | B60: 63 | C60: 8286 | D60: Agent opération | E60: Edition PART | F60: Sac | G60: =IFERROR(INDEX(code!$B$10:$B$13, MATCH(CENTRE_TEST!$E$52, code!$A$10:$A$13, 0)), "") -> ARRIVEE | H60: AMANA | I60: =CENTRE_TEST!$I$52 -> GLOBAL | J60: =UPPER(TRIM(SUBSTITUTE(G60," ",""))) & "|" & UPPER(TRIM(SUBSTITUTE(H60," ",""))) & "|" & UPPER(TRIM(SUBSTITUTE(I60," ",""))) -> ARRIVEE|AMANA|GLOBAL | K60: =IFERROR(SUMIFS(INPUT_VOLUMES!$D:$D,INPUT_VOLUMES!$A:$A,$G60,INPUT_VOLUMES!$B:$B,$H60,INPUT_VOLUMES!$C:$C,$I60),0) -> 50000 | L60: =K60/PARAMS!$B$2 -> 189.39394 | M60: =IF(F60="Sac", L60 / PARAMS!$B$6, L60 ) -> 37.878788 | N60: =IFERROR(INDEX(CENTRE_TEST!$L:$L,MATCH(P60,CENTRE_TEST!$M:$M,0)),0) -> 0.19 | O60: =IFERROR( M60 * (N60/60) * (PARAMS!$B$5 / 100), 0) -> 0.11994949 | P60: =UPPER(TRIM(SUBSTITUTE(SUBSTITUTE(E60,CHAR(10)," "),CHAR(13)," "))) -> EDITION PART
A61: 5025 | B61: 69 | C61: 8286 | D61: Agent opération | E61: Chargement VAN | F61: Sac | G61: =IFERROR(INDEX(code!$B$10:$B$13, MATCH(CENTRE_TEST!$E$52, code!$A$10:$A$13, 0)), "") -> ARRIVEE | H61: AMANA | I61: =CENTRE_TEST!$I$52 -> GLOBAL | J61: =UPPER(TRIM(SUBSTITUTE(G61," ",""))) & "|" & UPPER(TRIM(SUBSTITUTE(H61," ",""))) & "|" & UPPER(TRIM(SUBSTITUTE(I61," ",""))) -> ARRIVEE|AMANA|GLOBAL | K61: =IFERROR(SUMIFS(INPUT_VOLUMES!$D:$D,INPUT_VOLUMES!$A:$A,$G61,INPUT_VOLUMES!$B:$B,$H61,INPUT_VOLUMES!$C:$C,$I61),0) -> 50000 | L61: =K61/PARAMS!$B$2 -> 189.39394 | M61: =IF(F61="Sac", L61 / PARAMS!$B$6, L61 ) -> 37.878788 | N61: =IFERROR(INDEX(CENTRE_TEST!$L:$L,MATCH(P61,CENTRE_TEST!$M:$M,0)),0) -> 0.4 | O61: =IFERROR( M61 * (N61/60) * (PARAMS!$B$5 / 100), 0) -> 0.25252525 | P61: =UPPER(TRIM(SUBSTITUTE(SUBSTITUTE(E61,CHAR(10)," "),CHAR(13)," "))) -> CHARGEMENT VAN
A62: 5026 | B62: 70 | C62: 8286 | D62: Agent opération | E62: Démarrage Machine | F62: Machine | G62: =IFERROR(INDEX(code!$B$10:$B$13, MATCH(CENTRE_TEST!$E$62, code!$A$10:$A$13, 0)), "") -> ARRIVEE | I62: =CENTRE_TEST!$I$62 -> GLOBAL | J62: =UPPER(TRIM(SUBSTITUTE(G62," ",""))) & "|" & UPPER(TRIM(SUBSTITUTE(H62," ",""))) & "|" & UPPER(TRIM(SUBSTITUTE(I62," ",""))) -> ARRIVEE||GLOBAL | K62: =IFERROR(SUMIFS(INPUT_VOLUMES!$D:$D,INPUT_VOLUMES!$A:$A,$G62,INPUT_VOLUMES!$B:$B,$H62,INPUT_VOLUMES!$C:$C,$I62),0) -> 0 | L62: =K62/PARAMS!$B$2 -> 0 | M62: =IF(F62="Sac", L62 / PARAMS!$B$6, L62 ) -> 0 | N62: =IFERROR(INDEX(CENTRE_TEST!$L:$L,MATCH(P62,CENTRE_TEST!$M:$M,0)),0) -> 0.005 | O62: =IFERROR( M62 * (N62/60) * (PARAMS!$B$5 / 100), 0) -> 0 | P62: =UPPER(TRIM(SUBSTITUTE(SUBSTITUTE(E62,CHAR(10)," "),CHAR(13)," "))) -> DÉMARRAGE MACHINE
A63: 5027 | B63: 71 | C63: 8286 | D63: Agent opération | E63: Mise en service | F63: Machine | G63: =IFERROR(INDEX(code!$B$10:$B$13, MATCH(CENTRE_TEST!$E$63, code!$A$10:$A$13, 0)), "") -> ARRIVEE | H63: =IFERROR(INDEX([1]TACHES!$D:$D, MATCH(E63, [1]TACHES!$F:$F, 0)), "") | I63: =CENTRE_TEST!$I$63 -> GLOBAL | J63: =UPPER(TRIM(SUBSTITUTE(G63," ",""))) & "|" & UPPER(TRIM(SUBSTITUTE(H63," ",""))) & "|" & UPPER(TRIM(SUBSTITUTE(I63," ",""))) -> ARRIVEE||GLOBAL | K63: =IFERROR(SUMIFS(INPUT_VOLUMES!$D:$D,INPUT_VOLUMES!$A:$A,$G63,INPUT_VOLUMES!$B:$B,$H63,INPUT_VOLUMES!$C:$C,$I63),0) -> 0 | L63: =K63/PARAMS!$B$2 -> 0 | M63: =IF(F63="Sac", L63 / PARAMS!$B$6, L63 ) -> 0 | N63: =IFERROR(INDEX(CENTRE_TEST!$L:$L,MATCH(P63,CENTRE_TEST!$M:$M,0)),0) -> NULL | O63: =IFERROR( M63 * (N63/60) * (PARAMS!$B$5 / 100), 0) -> 0 | P63: =UPPER(TRIM(SUBSTITUTE(SUBSTITUTE(E63,CHAR(10)," "),CHAR(13)," "))) -> MISE EN SERVICE
A64: 5028 | B64: 72 | C64: 8286 | D64: Agent opération | E64: Pesage Courrier | F64: Courrier | G64: =IFERROR(INDEX(code!$B$10:$B$13, MATCH(CENTRE_TEST!$E$64, code!$A$10:$A$13, 0)), "") -> ARRIVEE | H64: CO | I64: =CENTRE_TEST!$I$64 -> GLOBAL | J64: =UPPER(TRIM(SUBSTITUTE(G64," ",""))) & "|" & UPPER(TRIM(SUBSTITUTE(H64," ",""))) & "|" & UPPER(TRIM(SUBSTITUTE(I64," ",""))) -> ARRIVEE|CO|GLOBAL | K64: =IFERROR(SUMIFS(INPUT_VOLUMES!$D:$D,INPUT_VOLUMES!$A:$A,$G64,INPUT_VOLUMES!$B:$B,$H64,INPUT_VOLUMES!$C:$C,$I64),0) -> 6000 | L64: =K64/PARAMS!$B$2 -> 22.727273 | M64: =IF(F64="Sac", L64 / PARAMS!$B$6, L64 ) -> 22.727273 | N64: =IFERROR(INDEX(CENTRE_TEST!$L:$L,MATCH(P64,CENTRE_TEST!$M:$M,0)),0) -> 0.16666667 | O64: =IFERROR( M64 * (N64/60) * (PARAMS!$B$5 / 100), 0) -> 0.063131313 | P64: =UPPER(TRIM(SUBSTITUTE(SUBSTITUTE(E64,CHAR(10)," "),CHAR(13)," "))) -> PESAGE COURRIER
A65: 5029 | B65: 73 | C65: 8286 | D65: Agent opération | E65: Traitement sur la machine MAG (Affranchissement) | F65: Courrier | G65: =IFERROR(INDEX(code!$B$10:$B$13, MATCH(CENTRE_TEST!$E$65, code!$A$10:$A$13, 0)), "") -> ARRIVEE | H65: CO | I65: =CENTRE_TEST!$I$65 -> GLOBAL | J65: =UPPER(TRIM(SUBSTITUTE(G65," ",""))) & "|" & UPPER(TRIM(SUBSTITUTE(H65," ",""))) & "|" & UPPER(TRIM(SUBSTITUTE(I65," ",""))) -> ARRIVEE|CO|GLOBAL | K65: =IFERROR(SUMIFS(INPUT_VOLUMES!$D:$D,INPUT_VOLUMES!$A:$A,$G65,INPUT_VOLUMES!$B:$B,$H65,INPUT_VOLUMES!$C:$C,$I65),0) -> 6000 | L65: =K65/PARAMS!$B$2 -> 22.727273 | M65: =IF(F65="Sac", L65 / PARAMS!$B$6, L65 ) -> 22.727273 | N65: =IFERROR(INDEX(CENTRE_TEST!$L:$L,MATCH(P65,CENTRE_TEST!$M:$M,0)),0) -> 0.16666667 | O65: =IFERROR( M65 * (N65/60) * (PARAMS!$B$5 / 100), 0) -> 0.063131313 | P65: =UPPER(TRIM(SUBSTITUTE(SUBSTITUTE(E65,CHAR(10)," "),CHAR(13)," "))) -> TRAITEMENT SUR LA MACHINE MAG (AFFRANCHISSEMENT)
A66: 5030 | B66: 74 | C66: 8286 | D66: Agent opération | E66: Réception | F66: Courrier | G66: =IFERROR(INDEX(code!$B$10:$B$13, MATCH(CENTRE_TEST!$E$66, code!$A$10:$A$13, 0)), "") -> ARRIVEE | H66: AMANA | I66: =CENTRE_TEST!$I$66 -> GLOBAL | J66: =UPPER(TRIM(SUBSTITUTE(G66," ",""))) & "|" & UPPER(TRIM(SUBSTITUTE(H66," ",""))) & "|" & UPPER(TRIM(SUBSTITUTE(I66," ",""))) -> ARRIVEE|AMANA|GLOBAL | K66: =IFERROR(SUMIFS(INPUT_VOLUMES!$D:$D,INPUT_VOLUMES!$A:$A,$G66,INPUT_VOLUMES!$B:$B,$H66,INPUT_VOLUMES!$C:$C,$I66),0) -> 50000 | L66: =K66/PARAMS!$B$2 -> 189.39394 | M66: =IF(F66="Sac", L66 / PARAMS!$B$6, L66 ) -> 189.39394 | N66: =IFERROR(INDEX(CENTRE_TEST!$L:$L,MATCH(P66,CENTRE_TEST!$M:$M,0)),0) -> 0.16 | O66: =IFERROR( M66 * (N66/60) * (PARAMS!$B$5 / 100), 0) -> 0.50505051 | P66: =UPPER(TRIM(SUBSTITUTE(SUBSTITUTE(E66,CHAR(10)," "),CHAR(13)," "))) -> RÉCEPTION
A67: 5031 | B67: 75 | C67: 8286 | D67: Agent opération | E67: Renseignement poids en manuel | F67: Courrier | G67: =IFERROR(INDEX(code!$B$10:$B$13, MATCH(CENTRE_TEST!$E$67, code!$A$10:$A$13, 0)), "") -> ARRIVEE | H67: CO | I67: =CENTRE_TEST!$I$67 -> GLOBAL | J67: =UPPER(TRIM(SUBSTITUTE(G67," ",""))) & "|" & UPPER(TRIM(SUBSTITUTE(H67," ",""))) & "|" & UPPER(TRIM(SUBSTITUTE(I67," ",""))) -> ARRIVEE|CO|GLOBAL | K67: =IFERROR(SUMIFS(INPUT_VOLUMES!$D:$D,INPUT_VOLUMES!$A:$A,$G67,INPUT_VOLUMES!$B:$B,$H67,INPUT_VOLUMES!$C:$C,$I67),0) -> 6000 | L67: =K67/PARAMS!$B$2 -> 22.727273 | M67: =IF(F67="Sac", L67 / PARAMS!$B$6, L67 ) -> 22.727273 | N67: =IFERROR(INDEX(CENTRE_TEST!$L:$L,MATCH(P67,CENTRE_TEST!$M:$M,0)),0) -> 0.38333333 | O67: =IFERROR( M67 * (N67/60) * (PARAMS!$B$5 / 100), 0) -> 0.14520202 | P67: =UPPER(TRIM(SUBSTITUTE(SUBSTITUTE(E67,CHAR(10)," "),CHAR(13)," "))) -> RENSEIGNEMENT POIDS EN MANUEL
A68: 5032 | B68: 76 | C68: 8286 | D68: Agent opération | E68: Saisie données sur SI COM | F68: Courrier | G68: =IFERROR(INDEX(code!$B$10:$B$13, MATCH(CENTRE_TEST!$E$68, code!$A$10:$A$13, 0)), "") -> ARRIVEE | H68: CO | I68: =CENTRE_TEST!$I$68 -> GLOBAL | J68: =UPPER(TRIM(SUBSTITUTE(G68," ",""))) & "|" & UPPER(TRIM(SUBSTITUTE(H68," ",""))) & "|" & UPPER(TRIM(SUBSTITUTE(I68," ",""))) -> ARRIVEE|CO|GLOBAL | K68: =IFERROR(SUMIFS(INPUT_VOLUMES!$D:$D,INPUT_VOLUMES!$A:$A,$G68,INPUT_VOLUMES!$B:$B,$H68,INPUT_VOLUMES!$C:$C,$I68),0) -> 6000 | L68: =K68/PARAMS!$B$2 -> 22.727273 | M68: =IF(F68="Sac", L68 / PARAMS!$B$6, L68 ) -> 22.727273 | N68: =IFERROR(INDEX(CENTRE_TEST!$L:$L,MATCH(P68,CENTRE_TEST!$M:$M,0)),0) -> NULL | O68: =IFERROR( M68 * (N68/60) * (PARAMS!$B$5 / 100), 0) -> 0 | P68: =UPPER(TRIM(SUBSTITUTE(SUBSTITUTE(E68,CHAR(10)," "),CHAR(13)," "))) -> SAISIE DONNÉES SUR SI COM
A69: 5033 | B69: 77 | C69: 8286 | D69: Agent opération | E69: Etat des emballages | F69: Courrier | G69: =IFERROR(INDEX(code!$B$10:$B$13, MATCH(CENTRE_TEST!$E$69, code!$A$10:$A$13, 0)), "") -> ARRIVEE | H69: CO | I69: =CENTRE_TEST!$I$69 -> GLOBAL | J69: =UPPER(TRIM(SUBSTITUTE(G69," ",""))) & "|" & UPPER(TRIM(SUBSTITUTE(H69," ",""))) & "|" & UPPER(TRIM(SUBSTITUTE(I69," ",""))) -> ARRIVEE|CO|GLOBAL | K69: =IFERROR(SUMIFS(INPUT_VOLUMES!$D:$D,INPUT_VOLUMES!$A:$A,$G69,INPUT_VOLUMES!$B:$B,$H69,INPUT_VOLUMES!$C:$C,$I69),0) -> 6000 | L69: =K69/PARAMS!$B$2 -> 22.727273 | M69: =IF(F69="Sac", L69 / PARAMS!$B$6, L69 ) -> 22.727273 | N69: =IFERROR(INDEX(CENTRE_TEST!$L:$L,MATCH(P69,CENTRE_TEST!$M:$M,0)),0) -> NULL | O69: =IFERROR( M69 * (N69/60) * (PARAMS!$B$5 / 100), 0) -> 0 | P69: =UPPER(TRIM(SUBSTITUTE(SUBSTITUTE(E69,CHAR(10)," "),CHAR(13)," "))) -> ETAT DES EMBALLAGES
A70: 5034 | B70: 78 | C70: 8286 | D70: Agent opération | E70: Etat remis aux agents guichet | F70: Courrier | G70: =IFERROR(INDEX(code!$B$10:$B$13, MATCH(CENTRE_TEST!$E$70, code!$A$10:$A$13, 0)), "") -> ARRIVEE | H70: CO | I70: =CENTRE_TEST!$I$70 -> GLOBAL | J70: =UPPER(TRIM(SUBSTITUTE(G70," ",""))) & "|" & UPPER(TRIM(SUBSTITUTE(H70," ",""))) & "|" & UPPER(TRIM(SUBSTITUTE(I70," ",""))) -> ARRIVEE|CO|GLOBAL | K70: =IFERROR(SUMIFS(INPUT_VOLUMES!$D:$D,INPUT_VOLUMES!$A:$A,$G70,INPUT_VOLUMES!$B:$B,$H70,INPUT_VOLUMES!$C:$C,$I70),0) -> 6000 | L70: =K70/PARAMS!$B$2 -> 22.727273 | M70: =IF(F70="Sac", L70 / PARAMS!$B$6, L70 ) -> 22.727273 | N70: =IFERROR(INDEX(CENTRE_TEST!$L:$L,MATCH(P70,CENTRE_TEST!$M:$M,0)),0) -> NULL | O70: =IFERROR( M70 * (N70/60) * (PARAMS!$B$5 / 100), 0) -> 0 | P70: =UPPER(TRIM(SUBSTITUTE(SUBSTITUTE(E70,CHAR(10)," "),CHAR(13)," "))) -> ETAT REMIS AUX AGENTS GUICHET

Sheet SUMMARY
A1: Indicateur | B1: Valeur
A2: Total_heures_necessaires | B2: =SUM(SIMULATION_CALC!$O:$O) -> 42.125631
A3: Heures_nettes_par_jour | B3: =PARAMS!$B$3 -> 8
A4: Heures_nettes_effectives | B4: =PARAMS!$B$3-(PARAMS!$B$4/60) -> 8
A5: ETP_calcule | B5: =B2 / B4 -> 5.2657039
A6: ETP_arrondi | B6: =ROUNDUP(B5,1) -> 5.3
